<?xml version='1.0' encoding='utf-8'?>
<Book osisId="1Cor" sblId="1Cor" name="1 К Коринфянам" shortName="1 Кор" orderIndex="45" chaptersCount="16" versesCount="437">
  <chapters>
    <Chapter osisId="1Cor.1" sblId="1Cor 1" name="1 К Коринфянам 1" shortName="1 Кор 1" orderIndex="0" versesCount="31">
      <verses>
        <Verse osisId="1Cor.1.1" sblId="1Cor 1:1" name="1 К Коринфянам 1:1" shortName="1 Кор 1:1" orderIndex="0">Павел, волею Божиею призванный Апостол Иисуса Христа, и Сосфен брат,</Verse>
        <Verse osisId="1Cor.1.2" sblId="1Cor 1:2" name="1 К Коринфянам 1:2" shortName="1 Кор 1:2" orderIndex="1">церкви Божией, находящейся в Коринфе, освященным во Христе Иисусе, призванным святым, со всеми призывающими имя Господа нашего Иисуса Христа, во всяком месте, у них и у нас:</Verse>
        <Verse osisId="1Cor.1.3" sblId="1Cor 1:3" name="1 К Коринфянам 1:3" shortName="1 Кор 1:3" orderIndex="2">благодать вам и мир от Бога Отца нашего и Господа Иисуса Христа.</Verse>
        <Verse osisId="1Cor.1.4" sblId="1Cor 1:4" name="1 К Коринфянам 1:4" shortName="1 Кор 1:4" orderIndex="3">Непрестанно благодарю Бога моего за вас, ради благодати Божией, дарованной вам во Христе Иисусе,</Verse>
        <Verse osisId="1Cor.1.5" sblId="1Cor 1:5" name="1 К Коринфянам 1:5" shortName="1 Кор 1:5" orderIndex="4">потому что в Нем вы обогатились всем, всяким словом и всяким познанием, –</Verse>
        <Verse osisId="1Cor.1.6" sblId="1Cor 1:6" name="1 К Коринфянам 1:6" shortName="1 Кор 1:6" orderIndex="5">ибо свидетельство Христово утвердилось в вас, –</Verse>
        <Verse osisId="1Cor.1.7" sblId="1Cor 1:7" name="1 К Коринфянам 1:7" shortName="1 Кор 1:7" orderIndex="6">так что вы не имеете недостатка ни в каком даровании, ожидая явления Господа нашего Иисуса Христа,</Verse>
        <Verse osisId="1Cor.1.8" sblId="1Cor 1:8" name="1 К Коринфянам 1:8" shortName="1 Кор 1:8" orderIndex="7">Который и утвердит вас до конца, [чтобы вам быть] неповинными в день Господа нашего Иисуса Христа.</Verse>
        <Verse osisId="1Cor.1.9" sblId="1Cor 1:9" name="1 К Коринфянам 1:9" shortName="1 Кор 1:9" orderIndex="8">Верен Бог, Которым вы призваны в общение Сына Его Иисуса Христа, Господа нашего.</Verse>
        <Verse osisId="1Cor.1.10" sblId="1Cor 1:10" name="1 К Коринфянам 1:10" shortName="1 Кор 1:10" orderIndex="9">Умоляю вас, братия, именем Господа нашего Иисуса Христа, чтобы все вы говорили одно, и не было между вами разделений, но чтобы вы соединены были в одном духе и в одних мыслях.</Verse>
        <Verse osisId="1Cor.1.11" sblId="1Cor 1:11" name="1 К Коринфянам 1:11" shortName="1 Кор 1:11" orderIndex="10">Ибо от [домашних] Хлоиных сделалось мне известным о вас, братия мои, что между вами есть споры.</Verse>
        <Verse osisId="1Cor.1.12" sblId="1Cor 1:12" name="1 К Коринфянам 1:12" shortName="1 Кор 1:12" orderIndex="11">Я разумею то, что у вас говорят: "я Павлов"; "я Аполлосов"; "я Кифин"; "а я Христов".</Verse>
        <Verse osisId="1Cor.1.13" sblId="1Cor 1:13" name="1 К Коринфянам 1:13" shortName="1 Кор 1:13" orderIndex="12">Разве разделился Христос? разве Павел распялся за вас? или во имя Павла вы крестились?</Verse>
        <Verse osisId="1Cor.1.14" sblId="1Cor 1:14" name="1 К Коринфянам 1:14" shortName="1 Кор 1:14" orderIndex="13">Благодарю Бога, что я никого из вас не крестил, кроме Криспа и Гаия,</Verse>
        <Verse osisId="1Cor.1.15" sblId="1Cor 1:15" name="1 К Коринфянам 1:15" shortName="1 Кор 1:15" orderIndex="14">дабы не сказал кто, что я крестил в мое имя.</Verse>
        <Verse osisId="1Cor.1.16" sblId="1Cor 1:16" name="1 К Коринфянам 1:16" shortName="1 Кор 1:16" orderIndex="15">Крестил я также Стефанов дом; а крестил ли еще кого, не знаю.</Verse>
        <Verse osisId="1Cor.1.17" sblId="1Cor 1:17" name="1 К Коринфянам 1:17" shortName="1 Кор 1:17" orderIndex="16">Ибо Христос послал меня не крестить, а благовествовать, не в премудрости слова, чтобы не упразднить креста Христова.</Verse>
        <Verse osisId="1Cor.1.18" sblId="1Cor 1:18" name="1 К Коринфянам 1:18" shortName="1 Кор 1:18" orderIndex="17">Ибо слово о кресте для погибающих юродство есть, а для нас, спасаемых, – сила Божия.</Verse>
        <Verse osisId="1Cor.1.19" sblId="1Cor 1:19" name="1 К Коринфянам 1:19" shortName="1 Кор 1:19" orderIndex="18">Ибо написано: погублю мудрость мудрецов, и разум разумных отвергну.</Verse>
        <Verse osisId="1Cor.1.20" sblId="1Cor 1:20" name="1 К Коринфянам 1:20" shortName="1 Кор 1:20" orderIndex="19">Где мудрец? где книжник? где совопросник века сего? Не обратил ли Бог мудрость мира сего в безумие?</Verse>
        <Verse osisId="1Cor.1.21" sblId="1Cor 1:21" name="1 К Коринфянам 1:21" shortName="1 Кор 1:21" orderIndex="20">Ибо когда мир [своею] мудростью не познал Бога в премудрости Божией, то благоугодно было Богу юродством проповеди спасти верующих.</Verse>
        <Verse osisId="1Cor.1.22" sblId="1Cor 1:22" name="1 К Коринфянам 1:22" shortName="1 Кор 1:22" orderIndex="21">Ибо и Иудеи требуют чудес, и Еллины ищут мудрости;</Verse>
        <Verse osisId="1Cor.1.23" sblId="1Cor 1:23" name="1 К Коринфянам 1:23" shortName="1 Кор 1:23" orderIndex="22">а мы проповедуем Христа распятого, для Иудеев соблазн, а для Еллинов безумие,</Verse>
        <Verse osisId="1Cor.1.24" sblId="1Cor 1:24" name="1 К Коринфянам 1:24" shortName="1 Кор 1:24" orderIndex="23">для самих же призванных, Иудеев и Еллинов, Христа, Божию силу и Божию премудрость;</Verse>
        <Verse osisId="1Cor.1.25" sblId="1Cor 1:25" name="1 К Коринфянам 1:25" shortName="1 Кор 1:25" orderIndex="24">потому что немудрое Божие премудрее человеков, и немощное Божие сильнее человеков.</Verse>
        <Verse osisId="1Cor.1.26" sblId="1Cor 1:26" name="1 К Коринфянам 1:26" shortName="1 Кор 1:26" orderIndex="25">Посмотрите, братия, кто вы, призванные: не много [из вас] мудрых по плоти, не много сильных, не много благородных;</Verse>
        <Verse osisId="1Cor.1.27" sblId="1Cor 1:27" name="1 К Коринфянам 1:27" shortName="1 Кор 1:27" orderIndex="26">но Бог избрал немудрое мира, чтобы посрамить мудрых, и немощное мира избрал Бог, чтобы посрамить сильное;</Verse>
        <Verse osisId="1Cor.1.28" sblId="1Cor 1:28" name="1 К Коринфянам 1:28" shortName="1 Кор 1:28" orderIndex="27">и незнатное мира и уничиженное и ничего не значащее избрал Бог, чтобы упразднить значащее, –</Verse>
        <Verse osisId="1Cor.1.29" sblId="1Cor 1:29" name="1 К Коринфянам 1:29" shortName="1 Кор 1:29" orderIndex="28">для того, чтобы никакая плоть не хвалилась пред Богом.</Verse>
        <Verse osisId="1Cor.1.30" sblId="1Cor 1:30" name="1 К Коринфянам 1:30" shortName="1 Кор 1:30" orderIndex="29">От Него и вы во Христе Иисусе, Который сделался для нас премудростью от Бога, праведностью и освящением и искуплением,</Verse>
        <Verse osisId="1Cor.1.31" sblId="1Cor 1:31" name="1 К Коринфянам 1:31" shortName="1 Кор 1:31" orderIndex="30">чтобы [было], как написано: хвалящийся хвались Господом.</Verse>
      </verses>
    </Chapter>
    <Chapter osisId="1Cor.2" sblId="1Cor 2" name="1 К Коринфянам 2" shortName="1 Кор 2" orderIndex="1" versesCount="16">
      <verses>
        <Verse osisId="1Cor.2.1" sblId="1Cor 2:1" name="1 К Коринфянам 2:1" shortName="1 Кор 2:1" orderIndex="0">И когда я приходил к вам, братия, приходил возвещать вам свидетельство Божие не в превосходстве слова или мудрости,</Verse>
        <Verse osisId="1Cor.2.2" sblId="1Cor 2:2" name="1 К Коринфянам 2:2" shortName="1 Кор 2:2" orderIndex="1">ибо я рассудил быть у вас незнающим ничего, кроме Иисуса Христа, и притом распятого,</Verse>
        <Verse osisId="1Cor.2.3" sblId="1Cor 2:3" name="1 К Коринфянам 2:3" shortName="1 Кор 2:3" orderIndex="2">и был я у вас в немощи и в страхе и в великом трепете.</Verse>
        <Verse osisId="1Cor.2.4" sblId="1Cor 2:4" name="1 К Коринфянам 2:4" shortName="1 Кор 2:4" orderIndex="3">И слово мое и проповедь моя не в убедительных словах человеческой мудрости, но в явлении духа и силы,</Verse>
        <Verse osisId="1Cor.2.5" sblId="1Cor 2:5" name="1 К Коринфянам 2:5" shortName="1 Кор 2:5" orderIndex="4">чтобы вера ваша [утверждалась] не на мудрости человеческой, но на силе Божией.</Verse>
        <Verse osisId="1Cor.2.6" sblId="1Cor 2:6" name="1 К Коринфянам 2:6" shortName="1 Кор 2:6" orderIndex="5">Мудрость же мы проповедуем между совершенными, но мудрость не века сего и не властей века сего преходящих,</Verse>
        <Verse osisId="1Cor.2.7" sblId="1Cor 2:7" name="1 К Коринфянам 2:7" shortName="1 Кор 2:7" orderIndex="6">но проповедуем премудрость Божию, тайную, сокровенную, которую предназначил Бог прежде веков к славе нашей,</Verse>
        <Verse osisId="1Cor.2.8" sblId="1Cor 2:8" name="1 К Коринфянам 2:8" shortName="1 Кор 2:8" orderIndex="7">которой никто из властей века сего не познал; ибо если бы познали, то не распяли бы Господа славы.</Verse>
        <Verse osisId="1Cor.2.9" sblId="1Cor 2:9" name="1 К Коринфянам 2:9" shortName="1 Кор 2:9" orderIndex="8">Но, как написано: не видел того глаз, не слышало ухо, и не приходило то на сердце человеку, что приготовил Бог любящим Его.</Verse>
        <Verse osisId="1Cor.2.10" sblId="1Cor 2:10" name="1 К Коринфянам 2:10" shortName="1 Кор 2:10" orderIndex="9">А нам Бог открыл [это] Духом Своим; ибо Дух все проницает, и глубины Божии.</Verse>
        <Verse osisId="1Cor.2.11" sblId="1Cor 2:11" name="1 К Коринфянам 2:11" shortName="1 Кор 2:11" orderIndex="10">Ибо кто из человеков знает, что в человеке, кроме духа человеческого, живущего в нем? Так и Божьего никто не знает, кроме Духа Божия.</Verse>
        <Verse osisId="1Cor.2.12" sblId="1Cor 2:12" name="1 К Коринфянам 2:12" shortName="1 Кор 2:12" orderIndex="11">Но мы приняли не духа мира сего, а Духа от Бога, дабы знать дарованное нам от Бога,</Verse>
        <Verse osisId="1Cor.2.13" sblId="1Cor 2:13" name="1 К Коринфянам 2:13" shortName="1 Кор 2:13" orderIndex="12">что и возвещаем не от человеческой мудрости изученными словами, но изученными от Духа Святаго, соображая духовное с духовным.</Verse>
        <Verse osisId="1Cor.2.14" sblId="1Cor 2:14" name="1 К Коринфянам 2:14" shortName="1 Кор 2:14" orderIndex="13">Душевный человек не принимает того, что от Духа Божия, потому что он почитает это безумием; и не может разуметь, потому что о сем [надобно] судить духовно.</Verse>
        <Verse osisId="1Cor.2.15" sblId="1Cor 2:15" name="1 К Коринфянам 2:15" shortName="1 Кор 2:15" orderIndex="14">Но духовный судит о всем, а о нем судить никто не может.</Verse>
        <Verse osisId="1Cor.2.16" sblId="1Cor 2:16" name="1 К Коринфянам 2:16" shortName="1 Кор 2:16" orderIndex="15">Ибо кто познал ум Господень, чтобы [мог] судить его? А мы имеем ум Христов.</Verse>
      </verses>
    </Chapter>
    <Chapter osisId="1Cor.3" sblId="1Cor 3" name="1 К Коринфянам 3" shortName="1 Кор 3" orderIndex="2" versesCount="23">
      <verses>
        <Verse osisId="1Cor.3.1" sblId="1Cor 3:1" name="1 К Коринфянам 3:1" shortName="1 Кор 3:1" orderIndex="0">И я не мог говорить с вами, братия, как с духовными, но как с плотскими, как с младенцами во Христе.</Verse>
        <Verse osisId="1Cor.3.2" sblId="1Cor 3:2" name="1 К Коринфянам 3:2" shortName="1 Кор 3:2" orderIndex="1">Я питал вас молоком, а не [твердою] пищею, ибо вы были еще не в силах, да и теперь не в силах,</Verse>
        <Verse osisId="1Cor.3.3" sblId="1Cor 3:3" name="1 К Коринфянам 3:3" shortName="1 Кор 3:3" orderIndex="2">потому что вы еще плотские. Ибо если между вами зависть, споры и разногласия, то не плотские ли вы? и не по человеческому ли [обычаю] поступаете?</Verse>
        <Verse osisId="1Cor.3.4" sblId="1Cor 3:4" name="1 К Коринфянам 3:4" shortName="1 Кор 3:4" orderIndex="3">Ибо когда один говорит: "я Павлов", а другой: "я Аполлосов", то не плотские ли вы?</Verse>
        <Verse osisId="1Cor.3.5" sblId="1Cor 3:5" name="1 К Коринфянам 3:5" shortName="1 Кор 3:5" orderIndex="4">Кто Павел? кто Аполлос? Они только служители, через которых вы уверовали, и притом поскольку каждому дал Господь.</Verse>
        <Verse osisId="1Cor.3.6" sblId="1Cor 3:6" name="1 К Коринфянам 3:6" shortName="1 Кор 3:6" orderIndex="5">Я насадил, Аполлос поливал, но возрастил Бог;</Verse>
        <Verse osisId="1Cor.3.7" sblId="1Cor 3:7" name="1 К Коринфянам 3:7" shortName="1 Кор 3:7" orderIndex="6">посему и насаждающий и поливающий есть ничто, а [все] Бог возращающий.</Verse>
        <Verse osisId="1Cor.3.8" sblId="1Cor 3:8" name="1 К Коринфянам 3:8" shortName="1 Кор 3:8" orderIndex="7">Насаждающий же и поливающий суть одно; но каждый получит свою награду по своему труду.</Verse>
        <Verse osisId="1Cor.3.9" sblId="1Cor 3:9" name="1 К Коринфянам 3:9" shortName="1 Кор 3:9" orderIndex="8">Ибо мы соработники у Бога, [а] вы Божия нива, Божие строение.</Verse>
        <Verse osisId="1Cor.3.10" sblId="1Cor 3:10" name="1 К Коринфянам 3:10" shortName="1 Кор 3:10" orderIndex="9">Я, по данной мне от Бога благодати, как мудрый строитель, положил основание, а другой строит на [нем]; но каждый смотри, как строит.</Verse>
        <Verse osisId="1Cor.3.11" sblId="1Cor 3:11" name="1 К Коринфянам 3:11" shortName="1 Кор 3:11" orderIndex="10">Ибо никто не может положить другого основания, кроме положенного, которое есть Иисус Христос.</Verse>
        <Verse osisId="1Cor.3.12" sblId="1Cor 3:12" name="1 К Коринфянам 3:12" shortName="1 Кор 3:12" orderIndex="11">Строит ли кто на этом основании из золота, серебра, драгоценных камней, дерева, сена, соломы, –</Verse>
        <Verse osisId="1Cor.3.13" sblId="1Cor 3:13" name="1 К Коринфянам 3:13" shortName="1 Кор 3:13" orderIndex="12">каждого дело обнаружится; ибо день покажет, потому что в огне открывается, и огонь испытает дело каждого, каково оно есть.</Verse>
        <Verse osisId="1Cor.3.14" sblId="1Cor 3:14" name="1 К Коринфянам 3:14" shortName="1 Кор 3:14" orderIndex="13">У кого дело, которое он строил, устоит, тот получит награду.</Verse>
        <Verse osisId="1Cor.3.15" sblId="1Cor 3:15" name="1 К Коринфянам 3:15" shortName="1 Кор 3:15" orderIndex="14">А у кого дело сгорит, тот потерпит урон; впрочем сам спасется, но так, как бы из огня.</Verse>
        <Verse osisId="1Cor.3.16" sblId="1Cor 3:16" name="1 К Коринфянам 3:16" shortName="1 Кор 3:16" orderIndex="15">Разве не знаете, что вы храм Божий, и Дух Божий живет в вас?</Verse>
        <Verse osisId="1Cor.3.17" sblId="1Cor 3:17" name="1 К Коринфянам 3:17" shortName="1 Кор 3:17" orderIndex="16">Если кто разорит храм Божий, того покарает Бог: ибо храм Божий свят; а этот [храм] – вы.</Verse>
        <Verse osisId="1Cor.3.18" sblId="1Cor 3:18" name="1 К Коринфянам 3:18" shortName="1 Кор 3:18" orderIndex="17">Никто не обольщай самого себя. Если кто из вас думает быть мудрым в веке сем, тот будь безумным, чтобы быть мудрым.</Verse>
        <Verse osisId="1Cor.3.19" sblId="1Cor 3:19" name="1 К Коринфянам 3:19" shortName="1 Кор 3:19" orderIndex="18">Ибо мудрость мира сего есть безумие пред Богом, как написано: уловляет мудрых в лукавстве их.</Verse>
        <Verse osisId="1Cor.3.20" sblId="1Cor 3:20" name="1 К Коринфянам 3:20" shortName="1 Кор 3:20" orderIndex="19">И еще: Господь знает умствования мудрецов, что они суетны.</Verse>
        <Verse osisId="1Cor.3.21" sblId="1Cor 3:21" name="1 К Коринфянам 3:21" shortName="1 Кор 3:21" orderIndex="20">Итак никто не хвались человеками, ибо все ваше:</Verse>
        <Verse osisId="1Cor.3.22" sblId="1Cor 3:22" name="1 К Коринфянам 3:22" shortName="1 Кор 3:22" orderIndex="21">Павел ли, или Аполлос, или Кифа, или мир, или жизнь, или смерть, или настоящее, или будущее, – все ваше;</Verse>
        <Verse osisId="1Cor.3.23" sblId="1Cor 3:23" name="1 К Коринфянам 3:23" shortName="1 Кор 3:23" orderIndex="22">вы же – Христовы, а Христос – Божий.</Verse>
      </verses>
    </Chapter>
    <Chapter osisId="1Cor.4" sblId="1Cor 4" name="1 К Коринфянам 4" shortName="1 Кор 4" orderIndex="3" versesCount="21">
      <verses>
        <Verse osisId="1Cor.4.1" sblId="1Cor 4:1" name="1 К Коринфянам 4:1" shortName="1 Кор 4:1" orderIndex="0">Итак каждый должен разуметь нас, как служителей Христовых и домостроителей таин Божиих.</Verse>
        <Verse osisId="1Cor.4.2" sblId="1Cor 4:2" name="1 К Коринфянам 4:2" shortName="1 Кор 4:2" orderIndex="1">От домостроителей же требуется, чтобы каждый оказался верным.</Verse>
        <Verse osisId="1Cor.4.3" sblId="1Cor 4:3" name="1 К Коринфянам 4:3" shortName="1 Кор 4:3" orderIndex="2">Для меня очень мало значит, как судите обо мне вы или [как] [судят] другие люди; я и сам не сужу о себе.</Verse>
        <Verse osisId="1Cor.4.4" sblId="1Cor 4:4" name="1 К Коринфянам 4:4" shortName="1 Кор 4:4" orderIndex="3">Ибо [хотя] я ничего не знаю за собою, но тем не оправдываюсь; судия же мне Господь.</Verse>
        <Verse osisId="1Cor.4.5" sblId="1Cor 4:5" name="1 К Коринфянам 4:5" shortName="1 Кор 4:5" orderIndex="4">Посему не судите никак прежде времени, пока не придет Господь, Который и осветит скрытое во мраке и обнаружит сердечные намерения, и тогда каждому будет похвала от Бога.</Verse>
        <Verse osisId="1Cor.4.6" sblId="1Cor 4:6" name="1 К Коринфянам 4:6" shortName="1 Кор 4:6" orderIndex="5">Это, братия, приложил я к себе и Аполлосу ради вас, чтобы вы научились от нас не мудрствовать сверх того, что написано, и не превозносились один перед другим.</Verse>
        <Verse osisId="1Cor.4.7" sblId="1Cor 4:7" name="1 К Коринфянам 4:7" shortName="1 Кор 4:7" orderIndex="6">Ибо кто отличает тебя? Что ты имеешь, чего бы не получил? А если получил, что хвалишься, как будто не получил?</Verse>
        <Verse osisId="1Cor.4.8" sblId="1Cor 4:8" name="1 К Коринфянам 4:8" shortName="1 Кор 4:8" orderIndex="7">Вы уже пресытились, вы уже обогатились, вы стали царствовать без нас. О, если бы вы [и в самом деле] царствовали, чтобы и нам с вами царствовать!</Verse>
        <Verse osisId="1Cor.4.9" sblId="1Cor 4:9" name="1 К Коринфянам 4:9" shortName="1 Кор 4:9" orderIndex="8">Ибо я думаю, что нам, последним посланникам, Бог судил быть как бы приговоренными к смерти, потому что мы сделались позорищем для мира, для Ангелов и человеков.</Verse>
        <Verse osisId="1Cor.4.10" sblId="1Cor 4:10" name="1 К Коринфянам 4:10" shortName="1 Кор 4:10" orderIndex="9">Мы безумны Христа ради, а вы мудры во Христе; мы немощны, а вы крепки; вы в славе, а мы в бесчестии.</Verse>
        <Verse osisId="1Cor.4.11" sblId="1Cor 4:11" name="1 К Коринфянам 4:11" shortName="1 Кор 4:11" orderIndex="10">Даже доныне терпим голод и жажду, и наготу и побои, и скитаемся,</Verse>
        <Verse osisId="1Cor.4.12" sblId="1Cor 4:12" name="1 К Коринфянам 4:12" shortName="1 Кор 4:12" orderIndex="11">и трудимся, работая своими руками. Злословят нас, мы благословляем; гонят нас, мы терпим;</Verse>
        <Verse osisId="1Cor.4.13" sblId="1Cor 4:13" name="1 К Коринфянам 4:13" shortName="1 Кор 4:13" orderIndex="12">хулят нас, мы молим; мы как сор для мира, [как] прах, всеми [попираемый] доныне.</Verse>
        <Verse osisId="1Cor.4.14" sblId="1Cor 4:14" name="1 К Коринфянам 4:14" shortName="1 Кор 4:14" orderIndex="13">Не к постыжению вашему пишу сие, но вразумляю вас, как возлюбленных детей моих.</Verse>
        <Verse osisId="1Cor.4.15" sblId="1Cor 4:15" name="1 К Коринфянам 4:15" shortName="1 Кор 4:15" orderIndex="14">Ибо, хотя у вас тысячи наставников во Христе, но не много отцов; я родил вас во Христе Иисусе благовествованием.</Verse>
        <Verse osisId="1Cor.4.16" sblId="1Cor 4:16" name="1 К Коринфянам 4:16" shortName="1 Кор 4:16" orderIndex="15">Посему умоляю вас: подражайте мне, как я Христу.</Verse>
        <Verse osisId="1Cor.4.17" sblId="1Cor 4:17" name="1 К Коринфянам 4:17" shortName="1 Кор 4:17" orderIndex="16">Для сего я послал к вам Тимофея, моего возлюбленного и верного в Господе сына, который напомнит вам о путях моих во Христе, как я учу везде во всякой церкви.</Verse>
        <Verse osisId="1Cor.4.18" sblId="1Cor 4:18" name="1 К Коринфянам 4:18" shortName="1 Кор 4:18" orderIndex="17">Как я не иду к вам, то некоторые [у вас] возгордились;</Verse>
        <Verse osisId="1Cor.4.19" sblId="1Cor 4:19" name="1 К Коринфянам 4:19" shortName="1 Кор 4:19" orderIndex="18">но я скоро приду к вам, если угодно будет Господу, и испытаю не слова возгордившихся, а силу,</Verse>
        <Verse osisId="1Cor.4.20" sblId="1Cor 4:20" name="1 К Коринфянам 4:20" shortName="1 Кор 4:20" orderIndex="19">ибо Царство Божие не в слове, а в силе.</Verse>
        <Verse osisId="1Cor.4.21" sblId="1Cor 4:21" name="1 К Коринфянам 4:21" shortName="1 Кор 4:21" orderIndex="20">Чего вы хотите? с жезлом придти к вам, или с любовью и духом кротости?</Verse>
      </verses>
    </Chapter>
    <Chapter osisId="1Cor.5" sblId="1Cor 5" name="1 К Коринфянам 5" shortName="1 Кор 5" orderIndex="4" versesCount="13">
      <verses>
        <Verse osisId="1Cor.5.1" sblId="1Cor 5:1" name="1 К Коринфянам 5:1" shortName="1 Кор 5:1" orderIndex="0">Есть верный слух, что у вас [появилось] блудодеяние, и притом такое блудодеяние, какого не слышно даже у язычников, что некто [вместо] [жены] имеет жену отца своего.</Verse>
        <Verse osisId="1Cor.5.2" sblId="1Cor 5:2" name="1 К Коринфянам 5:2" shortName="1 Кор 5:2" orderIndex="1">И вы возгордились, вместо того, чтобы лучше плакать, дабы изъят был из среды вас сделавший такое дело.</Verse>
        <Verse osisId="1Cor.5.3" sblId="1Cor 5:3" name="1 К Коринфянам 5:3" shortName="1 Кор 5:3" orderIndex="2">А я, отсутствуя телом, но присутствуя [у вас] духом, уже решил, как бы находясь у вас: сделавшего такое дело,</Verse>
        <Verse osisId="1Cor.5.4" sblId="1Cor 5:4" name="1 К Коринфянам 5:4" shortName="1 Кор 5:4" orderIndex="3">в собрании вашем во имя Господа нашего Иисуса Христа, обще с моим духом, силою Господа нашего Иисуса Христа,</Verse>
        <Verse osisId="1Cor.5.5" sblId="1Cor 5:5" name="1 К Коринфянам 5:5" shortName="1 Кор 5:5" orderIndex="4">предать сатане во измождение плоти, чтобы дух был спасен в день Господа нашего Иисуса Христа.</Verse>
        <Verse osisId="1Cor.5.6" sblId="1Cor 5:6" name="1 К Коринфянам 5:6" shortName="1 Кор 5:6" orderIndex="5">Нечем вам хвалиться. Разве не знаете, что малая закваска квасит все тесто?</Verse>
        <Verse osisId="1Cor.5.7" sblId="1Cor 5:7" name="1 К Коринфянам 5:7" shortName="1 Кор 5:7" orderIndex="6">Итак очистите старую закваску, чтобы быть вам новым тестом, так как вы бесквасны, ибо Пасха наша, Христос, заклан за нас.</Verse>
        <Verse osisId="1Cor.5.8" sblId="1Cor 5:8" name="1 К Коринфянам 5:8" shortName="1 Кор 5:8" orderIndex="7">Посему станем праздновать не со старою закваскою, не с закваскою порока и лукавства, но с опресноками чистоты и истины.</Verse>
        <Verse osisId="1Cor.5.9" sblId="1Cor 5:9" name="1 К Коринфянам 5:9" shortName="1 Кор 5:9" orderIndex="8">Я писал вам в послании – не сообщаться с блудниками;</Verse>
        <Verse osisId="1Cor.5.10" sblId="1Cor 5:10" name="1 К Коринфянам 5:10" shortName="1 Кор 5:10" orderIndex="9">впрочем не вообще с блудниками мира сего, или лихоимцами, или хищниками, или идолослужителями, ибо иначе надлежало бы вам выйти из мира [сего].</Verse>
        <Verse osisId="1Cor.5.11" sblId="1Cor 5:11" name="1 К Коринфянам 5:11" shortName="1 Кор 5:11" orderIndex="10">Но я писал вам не сообщаться с тем, кто, называясь братом, остается блудником, или лихоимцем, или идолослужителем, или злоречивым, или пьяницею, или хищником; с таким даже и не есть вместе.</Verse>
        <Verse osisId="1Cor.5.12" sblId="1Cor 5:12" name="1 К Коринфянам 5:12" shortName="1 Кор 5:12" orderIndex="11">Ибо что мне судить и внешних? Не внутренних ли вы судите?</Verse>
        <Verse osisId="1Cor.5.13" sblId="1Cor 5:13" name="1 К Коринфянам 5:13" shortName="1 Кор 5:13" orderIndex="12">Внешних же судит Бог. Итак, извергните развращенного из среды вас.</Verse>
      </verses>
    </Chapter>
    <Chapter osisId="1Cor.6" sblId="1Cor 6" name="1 К Коринфянам 6" shortName="1 Кор 6" orderIndex="5" versesCount="20">
      <verses>
        <Verse osisId="1Cor.6.1" sblId="1Cor 6:1" name="1 К Коринфянам 6:1" shortName="1 Кор 6:1" orderIndex="0">Как смеет кто у вас, имея дело с другим, судиться у нечестивых, а не у святых?</Verse>
        <Verse osisId="1Cor.6.2" sblId="1Cor 6:2" name="1 К Коринфянам 6:2" shortName="1 Кор 6:2" orderIndex="1">Разве не знаете, что святые будут судить мир? Если же вами будет судим мир, то неужели вы недостойны судить маловажные [дела]?</Verse>
        <Verse osisId="1Cor.6.3" sblId="1Cor 6:3" name="1 К Коринфянам 6:3" shortName="1 Кор 6:3" orderIndex="2">Разве не знаете, что мы будем судить ангелов, не тем ли более [дела] житейские?</Verse>
        <Verse osisId="1Cor.6.4" sblId="1Cor 6:4" name="1 К Коринфянам 6:4" shortName="1 Кор 6:4" orderIndex="3">А вы, когда имеете житейские тяжбы, поставляете [своими судьями] ничего не значащих в церкви.</Verse>
        <Verse osisId="1Cor.6.5" sblId="1Cor 6:5" name="1 К Коринфянам 6:5" shortName="1 Кор 6:5" orderIndex="4">К стыду вашему говорю: неужели нет между вами ни одного разумного, который мог бы рассудить между братьями своими?</Verse>
        <Verse osisId="1Cor.6.6" sblId="1Cor 6:6" name="1 К Коринфянам 6:6" shortName="1 Кор 6:6" orderIndex="5">Но брат с братом судится, и притом перед неверными.</Verse>
        <Verse osisId="1Cor.6.7" sblId="1Cor 6:7" name="1 К Коринфянам 6:7" shortName="1 Кор 6:7" orderIndex="6">И то уже весьма унизительно для вас, что вы имеете тяжбы между собою. Для чего бы вам лучше не оставаться обиженными? для чего бы вам лучше не терпеть лишения?</Verse>
        <Verse osisId="1Cor.6.8" sblId="1Cor 6:8" name="1 К Коринфянам 6:8" shortName="1 Кор 6:8" orderIndex="7">Но вы [сами] обижаете и отнимаете, и притом у братьев.</Verse>
        <Verse osisId="1Cor.6.9" sblId="1Cor 6:9" name="1 К Коринфянам 6:9" shortName="1 Кор 6:9" orderIndex="8">Или не знаете, что неправедные Царства Божия не наследуют? Не обманывайтесь: ни блудники, ни идолослужители, ни прелюбодеи, ни малакии, ни мужеложники,</Verse>
        <Verse osisId="1Cor.6.10" sblId="1Cor 6:10" name="1 К Коринфянам 6:10" shortName="1 Кор 6:10" orderIndex="9">ни воры, ни лихоимцы, ни пьяницы, ни злоречивые, ни хищники – Царства Божия не наследуют.</Verse>
        <Verse osisId="1Cor.6.11" sblId="1Cor 6:11" name="1 К Коринфянам 6:11" shortName="1 Кор 6:11" orderIndex="10">И такими были некоторые из вас; но омылись, но освятились, но оправдались именем Господа нашего Иисуса Христа и Духом Бога нашего.</Verse>
        <Verse osisId="1Cor.6.12" sblId="1Cor 6:12" name="1 К Коринфянам 6:12" shortName="1 Кор 6:12" orderIndex="11">Все мне позволительно, но не все полезно; все мне позволительно, но ничто не должно обладать мною.</Verse>
        <Verse osisId="1Cor.6.13" sblId="1Cor 6:13" name="1 К Коринфянам 6:13" shortName="1 Кор 6:13" orderIndex="12">Пища для чрева, и чрево для пищи; но Бог уничтожит и то и другое. Тело же не для блуда, но для Господа, и Господь для тела.</Verse>
        <Verse osisId="1Cor.6.14" sblId="1Cor 6:14" name="1 К Коринфянам 6:14" shortName="1 Кор 6:14" orderIndex="13">Бог воскресил Господа, воскресит и нас силою Своею.</Verse>
        <Verse osisId="1Cor.6.15" sblId="1Cor 6:15" name="1 К Коринфянам 6:15" shortName="1 Кор 6:15" orderIndex="14">Разве не знаете, что тела ваши суть члены Христовы? Итак отниму ли члены у Христа, чтобы сделать [их] членами блудницы? Да не будет!</Verse>
        <Verse osisId="1Cor.6.16" sblId="1Cor 6:16" name="1 К Коринфянам 6:16" shortName="1 Кор 6:16" orderIndex="15">Или не знаете, что совокупляющийся с блудницею становится одно тело [с нею]? ибо сказано: два будут одна плоть.</Verse>
        <Verse osisId="1Cor.6.17" sblId="1Cor 6:17" name="1 К Коринфянам 6:17" shortName="1 Кор 6:17" orderIndex="16">А соединяющийся с Господом есть один дух с Господом.</Verse>
        <Verse osisId="1Cor.6.18" sblId="1Cor 6:18" name="1 К Коринфянам 6:18" shortName="1 Кор 6:18" orderIndex="17">Бегайте блуда; всякий грех, какой делает человек, есть вне тела, а блудник грешит против собственного тела.</Verse>
        <Verse osisId="1Cor.6.19" sblId="1Cor 6:19" name="1 К Коринфянам 6:19" shortName="1 Кор 6:19" orderIndex="18">Не знаете ли, что тела ваши суть храм живущего в вас Святаго Духа, Которого имеете вы от Бога, и вы не свои?</Verse>
        <Verse osisId="1Cor.6.20" sblId="1Cor 6:20" name="1 К Коринфянам 6:20" shortName="1 Кор 6:20" orderIndex="19">Ибо вы куплены [дорогою] ценою. Посему прославляйте Бога и в телах ваших и в душах ваших, которые суть Божии.</Verse>
      </verses>
    </Chapter>
    <Chapter osisId="1Cor.7" sblId="1Cor 7" name="1 К Коринфянам 7" shortName="1 Кор 7" orderIndex="6" versesCount="40">
      <verses>
        <Verse osisId="1Cor.7.1" sblId="1Cor 7:1" name="1 К Коринфянам 7:1" shortName="1 Кор 7:1" orderIndex="0">А о чем вы писали ко мне, то хорошо человеку не касаться женщины.</Verse>
        <Verse osisId="1Cor.7.2" sblId="1Cor 7:2" name="1 К Коринфянам 7:2" shortName="1 Кор 7:2" orderIndex="1">Но, [во избежание] блуда, каждый имей свою жену, и каждая имей своего мужа.</Verse>
        <Verse osisId="1Cor.7.3" sblId="1Cor 7:3" name="1 К Коринфянам 7:3" shortName="1 Кор 7:3" orderIndex="2">Муж оказывай жене должное благорасположение; подобно и жена мужу.</Verse>
        <Verse osisId="1Cor.7.4" sblId="1Cor 7:4" name="1 К Коринфянам 7:4" shortName="1 Кор 7:4" orderIndex="3">Жена не властна над своим телом, но муж; равно и муж не властен над своим телом, но жена.</Verse>
        <Verse osisId="1Cor.7.5" sblId="1Cor 7:5" name="1 К Коринфянам 7:5" shortName="1 Кор 7:5" orderIndex="4">Не уклоняйтесь друг от друга, разве по согласию, на время, для упражнения в посте и молитве, а [потом] опять будьте вместе, чтобы не искушал вас сатана невоздержанием вашим.</Verse>
        <Verse osisId="1Cor.7.6" sblId="1Cor 7:6" name="1 К Коринфянам 7:6" shortName="1 Кор 7:6" orderIndex="5">Впрочем это сказано мною как позволение, а не как повеление.</Verse>
        <Verse osisId="1Cor.7.7" sblId="1Cor 7:7" name="1 К Коринфянам 7:7" shortName="1 Кор 7:7" orderIndex="6">Ибо желаю, чтобы все люди были, как и я; но каждый имеет свое дарование от Бога, один так, другой иначе.</Verse>
        <Verse osisId="1Cor.7.8" sblId="1Cor 7:8" name="1 К Коринфянам 7:8" shortName="1 Кор 7:8" orderIndex="7">Безбрачным же и вдовам говорю: хорошо им оставаться, как я.</Verse>
        <Verse osisId="1Cor.7.9" sblId="1Cor 7:9" name="1 К Коринфянам 7:9" shortName="1 Кор 7:9" orderIndex="8">Но если не [могут] воздержаться, пусть вступают в брак; ибо лучше вступить в брак, нежели разжигаться.</Verse>
        <Verse osisId="1Cor.7.10" sblId="1Cor 7:10" name="1 К Коринфянам 7:10" shortName="1 Кор 7:10" orderIndex="9">А вступившим в брак не я повелеваю, а Господь: жене не разводиться с мужем, –</Verse>
        <Verse osisId="1Cor.7.11" sblId="1Cor 7:11" name="1 К Коринфянам 7:11" shortName="1 Кор 7:11" orderIndex="10">если же разведется, то должна оставаться безбрачною, или примириться с мужем своим, – и мужу не оставлять жены [своей].</Verse>
        <Verse osisId="1Cor.7.12" sblId="1Cor 7:12" name="1 К Коринфянам 7:12" shortName="1 Кор 7:12" orderIndex="11">Прочим же я говорю, а не Господь: если какой брат имеет жену неверующую, и она согласна жить с ним, то он не должен оставлять ее;</Verse>
        <Verse osisId="1Cor.7.13" sblId="1Cor 7:13" name="1 К Коринфянам 7:13" shortName="1 Кор 7:13" orderIndex="12">и жена, которая имеет мужа неверующего, и он согласен жить с нею, не должна оставлять его.</Verse>
        <Verse osisId="1Cor.7.14" sblId="1Cor 7:14" name="1 К Коринфянам 7:14" shortName="1 Кор 7:14" orderIndex="13">Ибо неверующий муж освящается женою верующею, и жена неверующая освящается мужем верующим. Иначе дети ваши были бы нечисты, а теперь святы.</Verse>
        <Verse osisId="1Cor.7.15" sblId="1Cor 7:15" name="1 К Коринфянам 7:15" shortName="1 Кор 7:15" orderIndex="14">Если же неверующий [хочет] развестись, пусть разводится; брат или сестра в таких [случаях] не связаны; к миру призвал нас Господь.</Verse>
        <Verse osisId="1Cor.7.16" sblId="1Cor 7:16" name="1 К Коринфянам 7:16" shortName="1 Кор 7:16" orderIndex="15">Почему ты знаешь, жена, не спасешь ли мужа? Или ты, муж, почему знаешь, не спасешь ли жены?</Verse>
        <Verse osisId="1Cor.7.17" sblId="1Cor 7:17" name="1 К Коринфянам 7:17" shortName="1 Кор 7:17" orderIndex="16">Только каждый поступай так, как Бог ему определил, и каждый, как Господь призвал. Так я повелеваю по всем церквам.</Verse>
        <Verse osisId="1Cor.7.18" sblId="1Cor 7:18" name="1 К Коринфянам 7:18" shortName="1 Кор 7:18" orderIndex="17">Призван ли кто обрезанным, не скрывайся; призван ли кто необрезанным, не обрезывайся.</Verse>
        <Verse osisId="1Cor.7.19" sblId="1Cor 7:19" name="1 К Коринфянам 7:19" shortName="1 Кор 7:19" orderIndex="18">Обрезание ничто и необрезание ничто, но [все] в соблюдении заповедей Божиих.</Verse>
        <Verse osisId="1Cor.7.20" sblId="1Cor 7:20" name="1 К Коринфянам 7:20" shortName="1 Кор 7:20" orderIndex="19">Каждый оставайся в том звании, в котором призван.</Verse>
        <Verse osisId="1Cor.7.21" sblId="1Cor 7:21" name="1 К Коринфянам 7:21" shortName="1 Кор 7:21" orderIndex="20">Рабом ли ты призван, не смущайся; но если и можешь сделаться свободным, то лучшим воспользуйся.</Verse>
        <Verse osisId="1Cor.7.22" sblId="1Cor 7:22" name="1 К Коринфянам 7:22" shortName="1 Кор 7:22" orderIndex="21">Ибо раб, призванный в Господе, есть свободный Господа; равно и призванный свободным есть раб Христов.</Verse>
        <Verse osisId="1Cor.7.23" sblId="1Cor 7:23" name="1 К Коринфянам 7:23" shortName="1 Кор 7:23" orderIndex="22">Вы куплены [дорогою] ценою; не делайтесь рабами человеков.</Verse>
        <Verse osisId="1Cor.7.24" sblId="1Cor 7:24" name="1 К Коринфянам 7:24" shortName="1 Кор 7:24" orderIndex="23">В каком [звании] кто призван, братия, в том каждый и оставайся пред Богом.</Verse>
        <Verse osisId="1Cor.7.25" sblId="1Cor 7:25" name="1 К Коринфянам 7:25" shortName="1 Кор 7:25" orderIndex="24">Относительно девства я не имею повеления Господня, а даю совет, как получивший от Господа милость быть [Ему] верным.</Verse>
        <Verse osisId="1Cor.7.26" sblId="1Cor 7:26" name="1 К Коринфянам 7:26" shortName="1 Кор 7:26" orderIndex="25">По настоящей нужде за лучшее признаю, что хорошо человеку оставаться так.</Verse>
        <Verse osisId="1Cor.7.27" sblId="1Cor 7:27" name="1 К Коринфянам 7:27" shortName="1 Кор 7:27" orderIndex="26">Соединен ли ты с женой? не ищи развода. Остался ли без жены? не ищи жены.</Verse>
        <Verse osisId="1Cor.7.28" sblId="1Cor 7:28" name="1 К Коринфянам 7:28" shortName="1 Кор 7:28" orderIndex="27">Впрочем, если и женишься, не согрешишь; и если девица выйдет замуж, не согрешит. Но таковые будут иметь скорби по плоти; а мне вас жаль.</Verse>
        <Verse osisId="1Cor.7.29" sblId="1Cor 7:29" name="1 К Коринфянам 7:29" shortName="1 Кор 7:29" orderIndex="28">Я вам сказываю, братия: время уже коротко, так что имеющие жен должны быть, как не имеющие;</Verse>
        <Verse osisId="1Cor.7.30" sblId="1Cor 7:30" name="1 К Коринфянам 7:30" shortName="1 Кор 7:30" orderIndex="29">и плачущие, как не плачущие; и радующиеся, как не радующиеся; и покупающие, как не приобретающие;</Verse>
        <Verse osisId="1Cor.7.31" sblId="1Cor 7:31" name="1 К Коринфянам 7:31" shortName="1 Кор 7:31" orderIndex="30">и пользующиеся миром сим, как не пользующиеся; ибо проходит образ мира сего.</Verse>
        <Verse osisId="1Cor.7.32" sblId="1Cor 7:32" name="1 К Коринфянам 7:32" shortName="1 Кор 7:32" orderIndex="31">А я хочу, чтобы вы были без забот. Неженатый заботится о Господнем, как угодить Господу;</Verse>
        <Verse osisId="1Cor.7.33" sblId="1Cor 7:33" name="1 К Коринфянам 7:33" shortName="1 Кор 7:33" orderIndex="32">а женатый заботится о мирском, как угодить жене. Есть разность между замужнею и девицею:</Verse>
        <Verse osisId="1Cor.7.34" sblId="1Cor 7:34" name="1 К Коринфянам 7:34" shortName="1 Кор 7:34" orderIndex="33">незамужняя заботится о Господнем, как угодить Господу, чтобы быть святою и телом и духом; а замужняя заботится о мирском, как угодить мужу.</Verse>
        <Verse osisId="1Cor.7.35" sblId="1Cor 7:35" name="1 К Коринфянам 7:35" shortName="1 Кор 7:35" orderIndex="34">Говорю это для вашей же пользы, не с тем, чтобы наложить на вас узы, но чтобы вы благочинно и непрестанно [служили] Господу без развлечения.</Verse>
        <Verse osisId="1Cor.7.36" sblId="1Cor 7:36" name="1 К Коринфянам 7:36" shortName="1 Кор 7:36" orderIndex="35">Если же кто почитает неприличным для своей девицы то, чтобы она, будучи в зрелом возрасте, оставалась так, тот пусть делает, как хочет: не согрешит; пусть [таковые] выходят замуж.</Verse>
        <Verse osisId="1Cor.7.37" sblId="1Cor 7:37" name="1 К Коринфянам 7:37" shortName="1 Кор 7:37" orderIndex="36">Но кто непоколебимо тверд в сердце своем и, не будучи стесняем нуждою, но будучи властен в своей воле, решился в сердце своем соблюдать свою деву, тот хорошо поступает.</Verse>
        <Verse osisId="1Cor.7.38" sblId="1Cor 7:38" name="1 К Коринфянам 7:38" shortName="1 Кор 7:38" orderIndex="37">Посему выдающий замуж свою девицу поступает хорошо; а не выдающий поступает лучше.</Verse>
        <Verse osisId="1Cor.7.39" sblId="1Cor 7:39" name="1 К Коринфянам 7:39" shortName="1 Кор 7:39" orderIndex="38">Жена связана законом, доколе жив муж ее; если же муж ее умрет, свободна выйти, за кого хочет, только в Господе.</Verse>
        <Verse osisId="1Cor.7.40" sblId="1Cor 7:40" name="1 К Коринфянам 7:40" shortName="1 Кор 7:40" orderIndex="39">Но она блаженнее, если останется так, по моему совету; а думаю, и я имею Духа Божия.</Verse>
      </verses>
    </Chapter>
    <Chapter osisId="1Cor.8" sblId="1Cor 8" name="1 К Коринфянам 8" shortName="1 Кор 8" orderIndex="7" versesCount="13">
      <verses>
        <Verse osisId="1Cor.8.1" sblId="1Cor 8:1" name="1 К Коринфянам 8:1" shortName="1 Кор 8:1" orderIndex="0">О идоложертвенных [яствах] мы знаем, потому что мы все имеем знание; но знание надмевает, а любовь назидает.</Verse>
        <Verse osisId="1Cor.8.2" sblId="1Cor 8:2" name="1 К Коринфянам 8:2" shortName="1 Кор 8:2" orderIndex="1">Кто думает, что он знает что–нибудь, тот ничего еще не знает так, как должно знать.</Verse>
        <Verse osisId="1Cor.8.3" sblId="1Cor 8:3" name="1 К Коринфянам 8:3" shortName="1 Кор 8:3" orderIndex="2">Но кто любит Бога, тому дано знание от Него.</Verse>
        <Verse osisId="1Cor.8.4" sblId="1Cor 8:4" name="1 К Коринфянам 8:4" shortName="1 Кор 8:4" orderIndex="3">Итак об употреблении в пищу идоложертвенного мы знаем, что идол в мире ничто, и что нет иного Бога, кроме Единого.</Verse>
        <Verse osisId="1Cor.8.5" sblId="1Cor 8:5" name="1 К Коринфянам 8:5" shortName="1 Кор 8:5" orderIndex="4">Ибо хотя и есть так называемые боги, или на небе, или на земле, так как есть много богов и господ много, –</Verse>
        <Verse osisId="1Cor.8.6" sblId="1Cor 8:6" name="1 К Коринфянам 8:6" shortName="1 Кор 8:6" orderIndex="5">но у нас один Бог Отец, из Которого все, и мы для Него, и один Господь Иисус Христос, Которым все, и мы Им.</Verse>
        <Verse osisId="1Cor.8.7" sblId="1Cor 8:7" name="1 К Коринфянам 8:7" shortName="1 Кор 8:7" orderIndex="6">Но не у всех [такое] знание: некоторые и доныне с совестью, [признающею] идолов, едят [идоложертвенное] как жертвы идольские, и совесть их, будучи немощна, оскверняется.</Verse>
        <Verse osisId="1Cor.8.8" sblId="1Cor 8:8" name="1 К Коринфянам 8:8" shortName="1 Кор 8:8" orderIndex="7">Пища не приближает нас к Богу: ибо, едим ли мы, ничего не приобретаем; не едим ли, ничего не теряем.</Verse>
        <Verse osisId="1Cor.8.9" sblId="1Cor 8:9" name="1 К Коринфянам 8:9" shortName="1 Кор 8:9" orderIndex="8">Берегитесь однако же, чтобы эта свобода ваша не послужила соблазном для немощных.</Verse>
        <Verse osisId="1Cor.8.10" sblId="1Cor 8:10" name="1 К Коринфянам 8:10" shortName="1 Кор 8:10" orderIndex="9">Ибо если кто–нибудь увидит, что ты, имея знание, сидишь за столом в капище, то совесть его, как немощного, не расположит ли и его есть идоложертвенное?</Verse>
        <Verse osisId="1Cor.8.11" sblId="1Cor 8:11" name="1 К Коринфянам 8:11" shortName="1 Кор 8:11" orderIndex="10">И от знания твоего погибнет немощный брат, за которого умер Христос.</Verse>
        <Verse osisId="1Cor.8.12" sblId="1Cor 8:12" name="1 К Коринфянам 8:12" shortName="1 Кор 8:12" orderIndex="11">А согрешая таким образом против братьев и уязвляя немощную совесть их, вы согрешаете против Христа.</Verse>
        <Verse osisId="1Cor.8.13" sblId="1Cor 8:13" name="1 К Коринфянам 8:13" shortName="1 Кор 8:13" orderIndex="12">И потому, если пища соблазняет брата моего, не буду есть мяса вовек, чтобы не соблазнить брата моего.</Verse>
      </verses>
    </Chapter>
    <Chapter osisId="1Cor.9" sblId="1Cor 9" name="1 К Коринфянам 9" shortName="1 Кор 9" orderIndex="8" versesCount="27">
      <verses>
        <Verse osisId="1Cor.9.1" sblId="1Cor 9:1" name="1 К Коринфянам 9:1" shortName="1 Кор 9:1" orderIndex="0">Не Апостол ли я? Не свободен ли я? Не видел ли я Иисуса Христа, Господа нашего? Не мое ли дело вы в Господе?</Verse>
        <Verse osisId="1Cor.9.2" sblId="1Cor 9:2" name="1 К Коринфянам 9:2" shortName="1 Кор 9:2" orderIndex="1">Если для других я не Апостол, то для вас [Апостол]; ибо печать моего апостольства – вы в Господе.</Verse>
        <Verse osisId="1Cor.9.3" sblId="1Cor 9:3" name="1 К Коринфянам 9:3" shortName="1 Кор 9:3" orderIndex="2">Вот мое защищение против осуждающих меня.</Verse>
        <Verse osisId="1Cor.9.4" sblId="1Cor 9:4" name="1 К Коринфянам 9:4" shortName="1 Кор 9:4" orderIndex="3">Или мы не имеем власти есть и пить?</Verse>
        <Verse osisId="1Cor.9.5" sblId="1Cor 9:5" name="1 К Коринфянам 9:5" shortName="1 Кор 9:5" orderIndex="4">Или не имеем власти иметь спутницею сестру жену, как и прочие Апостолы, и братья Господни, и Кифа?</Verse>
        <Verse osisId="1Cor.9.6" sblId="1Cor 9:6" name="1 К Коринфянам 9:6" shortName="1 Кор 9:6" orderIndex="5">Или один я и Варнава не имеем власти не работать?</Verse>
        <Verse osisId="1Cor.9.7" sblId="1Cor 9:7" name="1 К Коринфянам 9:7" shortName="1 Кор 9:7" orderIndex="6">Какой воин служит когда–либо на своем содержании? Кто, насадив виноград, не ест плодов его? Кто, пася стадо, не ест молока от стада?</Verse>
        <Verse osisId="1Cor.9.8" sblId="1Cor 9:8" name="1 К Коринфянам 9:8" shortName="1 Кор 9:8" orderIndex="7">По человеческому ли только [рассуждению] я это говорю? Не то же ли говорит и закон?</Verse>
        <Verse osisId="1Cor.9.9" sblId="1Cor 9:9" name="1 К Коринфянам 9:9" shortName="1 Кор 9:9" orderIndex="8">Ибо в Моисеевом законе написано: не заграждай рта у вола молотящего. О волах ли печется Бог?</Verse>
        <Verse osisId="1Cor.9.10" sblId="1Cor 9:10" name="1 К Коринфянам 9:10" shortName="1 Кор 9:10" orderIndex="9">Или, конечно, для нас говорится? Так, для нас это написано; ибо, кто пашет, должен пахать с надеждою, и кто молотит, [должен молотить] с надеждою получить ожидаемое.</Verse>
        <Verse osisId="1Cor.9.11" sblId="1Cor 9:11" name="1 К Коринфянам 9:11" shortName="1 Кор 9:11" orderIndex="10">Если мы посеяли в вас духовное, велико ли то, если пожнем у вас телесное?</Verse>
        <Verse osisId="1Cor.9.12" sblId="1Cor 9:12" name="1 К Коринфянам 9:12" shortName="1 Кор 9:12" orderIndex="11">Если другие имеют у вас власть, не паче ли мы? Однако мы не пользовались сею властью, но все переносим, дабы не поставить какой преграды благовествованию Христову.</Verse>
        <Verse osisId="1Cor.9.13" sblId="1Cor 9:13" name="1 К Коринфянам 9:13" shortName="1 Кор 9:13" orderIndex="12">Разве не знаете, что священнодействующие питаются от святилища? что служащие жертвеннику берут долю от жертвенника?</Verse>
        <Verse osisId="1Cor.9.14" sblId="1Cor 9:14" name="1 К Коринфянам 9:14" shortName="1 Кор 9:14" orderIndex="13">Так и Господь повелел проповедующим Евангелие жить от благовествования.</Verse>
        <Verse osisId="1Cor.9.15" sblId="1Cor 9:15" name="1 К Коринфянам 9:15" shortName="1 Кор 9:15" orderIndex="14">Но я не пользовался ничем таковым. И написал это не для того, чтобы так было для меня. Ибо для меня лучше умереть, нежели чтобы кто уничтожил похвалу мою.</Verse>
        <Verse osisId="1Cor.9.16" sblId="1Cor 9:16" name="1 К Коринфянам 9:16" shortName="1 Кор 9:16" orderIndex="15">Ибо если я благовествую, то нечем мне хвалиться, потому что это необходимая [обязанность] моя, и горе мне, если не благовествую!</Verse>
        <Verse osisId="1Cor.9.17" sblId="1Cor 9:17" name="1 К Коринфянам 9:17" shortName="1 Кор 9:17" orderIndex="16">Ибо если делаю это добровольно, то [буду] иметь награду; а если недобровольно, то [исполняю только] вверенное мне служение.</Verse>
        <Verse osisId="1Cor.9.18" sblId="1Cor 9:18" name="1 К Коринфянам 9:18" shortName="1 Кор 9:18" orderIndex="17">За что же мне награда? За то, что, проповедуя Евангелие, благовествую о Христе безмездно, не пользуясь моею властью в благовествовании.</Verse>
        <Verse osisId="1Cor.9.19" sblId="1Cor 9:19" name="1 К Коринфянам 9:19" shortName="1 Кор 9:19" orderIndex="18">Ибо, будучи свободен от всех, я всем поработил себя, дабы больше приобрести:</Verse>
        <Verse osisId="1Cor.9.20" sblId="1Cor 9:20" name="1 К Коринфянам 9:20" shortName="1 Кор 9:20" orderIndex="19">для Иудеев я был как Иудей, чтобы приобрести Иудеев; для подзаконных был как подзаконный, чтобы приобрести подзаконных;</Verse>
        <Verse osisId="1Cor.9.21" sblId="1Cor 9:21" name="1 К Коринфянам 9:21" shortName="1 Кор 9:21" orderIndex="20">для чуждых закона – как чуждый закона, – не будучи чужд закона пред Богом, но подзаконен Христу, – чтобы приобрести чуждых закона;</Verse>
        <Verse osisId="1Cor.9.22" sblId="1Cor 9:22" name="1 К Коринфянам 9:22" shortName="1 Кор 9:22" orderIndex="21">для немощных был как немощный, чтобы приобрести немощных. Для всех я сделался всем, чтобы спасти по крайней мере некоторых.</Verse>
        <Verse osisId="1Cor.9.23" sblId="1Cor 9:23" name="1 К Коринфянам 9:23" shortName="1 Кор 9:23" orderIndex="22">Сие же делаю для Евангелия, чтобы быть соучастником его.</Verse>
        <Verse osisId="1Cor.9.24" sblId="1Cor 9:24" name="1 К Коринфянам 9:24" shortName="1 Кор 9:24" orderIndex="23">Не знаете ли, что бегущие на ристалище бегут все, но один получает награду? Так бегите, чтобы получить.</Verse>
        <Verse osisId="1Cor.9.25" sblId="1Cor 9:25" name="1 К Коринфянам 9:25" shortName="1 Кор 9:25" orderIndex="24">Все подвижники воздерживаются от всего: те для получения венца тленного, а мы – нетленного.</Verse>
        <Verse osisId="1Cor.9.26" sblId="1Cor 9:26" name="1 К Коринфянам 9:26" shortName="1 Кор 9:26" orderIndex="25">И потому я бегу не так, как на неверное, бьюсь не так, чтобы только бить воздух;</Verse>
        <Verse osisId="1Cor.9.27" sblId="1Cor 9:27" name="1 К Коринфянам 9:27" shortName="1 Кор 9:27" orderIndex="26">но усмиряю и порабощаю тело мое, дабы, проповедуя другим, самому не остаться недостойным.</Verse>
      </verses>
    </Chapter>
    <Chapter osisId="1Cor.10" sblId="1Cor 10" name="1 К Коринфянам 10" shortName="1 Кор 10" orderIndex="9" versesCount="33">
      <verses>
        <Verse osisId="1Cor.10.1" sblId="1Cor 10:1" name="1 К Коринфянам 10:1" shortName="1 Кор 10:1" orderIndex="0">Не хочу оставить вас, братия, в неведении, что отцы наши все были под облаком, и все прошли сквозь море;</Verse>
        <Verse osisId="1Cor.10.2" sblId="1Cor 10:2" name="1 К Коринфянам 10:2" shortName="1 Кор 10:2" orderIndex="1">и все крестились в Моисея в облаке и в море;</Verse>
        <Verse osisId="1Cor.10.3" sblId="1Cor 10:3" name="1 К Коринфянам 10:3" shortName="1 Кор 10:3" orderIndex="2">и все ели одну и ту же духовную пищу;</Verse>
        <Verse osisId="1Cor.10.4" sblId="1Cor 10:4" name="1 К Коринфянам 10:4" shortName="1 Кор 10:4" orderIndex="3">и все пили одно и то же духовное питие: ибо пили из духовного последующего камня; камень же был Христос.</Verse>
        <Verse osisId="1Cor.10.5" sblId="1Cor 10:5" name="1 К Коринфянам 10:5" shortName="1 Кор 10:5" orderIndex="4">Но не о многих из них благоволил Бог, ибо они поражены были в пустыне.</Verse>
        <Verse osisId="1Cor.10.6" sblId="1Cor 10:6" name="1 К Коринфянам 10:6" shortName="1 Кор 10:6" orderIndex="5">А это были образы для нас, чтобы мы не были похотливы на злое, как они были похотливы.</Verse>
        <Verse osisId="1Cor.10.7" sblId="1Cor 10:7" name="1 К Коринфянам 10:7" shortName="1 Кор 10:7" orderIndex="6">Не будьте также идолопоклонниками, как некоторые из них, о которых написано: народ сел есть и пить, и встал играть.</Verse>
        <Verse osisId="1Cor.10.8" sblId="1Cor 10:8" name="1 К Коринфянам 10:8" shortName="1 Кор 10:8" orderIndex="7">Не станем блудодействовать, как некоторые из них блудодействовали, и в один день погибло их двадцать три тысячи.</Verse>
        <Verse osisId="1Cor.10.9" sblId="1Cor 10:9" name="1 К Коринфянам 10:9" shortName="1 Кор 10:9" orderIndex="8">Не станем искушать Христа, как некоторые из них искушали и погибли от змей.</Verse>
        <Verse osisId="1Cor.10.10" sblId="1Cor 10:10" name="1 К Коринфянам 10:10" shortName="1 Кор 10:10" orderIndex="9">Не ропщите, как некоторые из них роптали и погибли от истребителя.</Verse>
        <Verse osisId="1Cor.10.11" sblId="1Cor 10:11" name="1 К Коринфянам 10:11" shortName="1 Кор 10:11" orderIndex="10">Все это происходило с ними, [как] образы; а описано в наставление нам, достигшим последних веков.</Verse>
        <Verse osisId="1Cor.10.12" sblId="1Cor 10:12" name="1 К Коринфянам 10:12" shortName="1 Кор 10:12" orderIndex="11">Посему, кто думает, что он стоит, берегись, чтобы не упасть.</Verse>
        <Verse osisId="1Cor.10.13" sblId="1Cor 10:13" name="1 К Коринфянам 10:13" shortName="1 Кор 10:13" orderIndex="12">Вас постигло искушение не иное, как человеческое; и верен Бог, Который не попустит вам быть искушаемыми сверх сил, но при искушении даст и облегчение, так чтобы вы могли перенести.</Verse>
        <Verse osisId="1Cor.10.14" sblId="1Cor 10:14" name="1 К Коринфянам 10:14" shortName="1 Кор 10:14" orderIndex="13">Итак, возлюбленные мои, убегайте идолослужения.</Verse>
        <Verse osisId="1Cor.10.15" sblId="1Cor 10:15" name="1 К Коринфянам 10:15" shortName="1 Кор 10:15" orderIndex="14">Я говорю [вам] как рассудительным; сами рассудите о том, что говорю.</Verse>
        <Verse osisId="1Cor.10.16" sblId="1Cor 10:16" name="1 К Коринфянам 10:16" shortName="1 Кор 10:16" orderIndex="15">Чаша благословения, которую благословляем, не есть ли приобщение Крови Христовой? Хлеб, который преломляем, не есть ли приобщение Тела Христова?</Verse>
        <Verse osisId="1Cor.10.17" sblId="1Cor 10:17" name="1 К Коринфянам 10:17" shortName="1 Кор 10:17" orderIndex="16">Один хлеб, и мы многие одно тело; ибо все причащаемся от одного хлеба.</Verse>
        <Verse osisId="1Cor.10.18" sblId="1Cor 10:18" name="1 К Коринфянам 10:18" shortName="1 Кор 10:18" orderIndex="17">Посмотрите на Израиля по плоти: те, которые едят жертвы, не участники ли жертвенника?</Verse>
        <Verse osisId="1Cor.10.19" sblId="1Cor 10:19" name="1 К Коринфянам 10:19" shortName="1 Кор 10:19" orderIndex="18">Что же я говорю? То ли, что идол есть что–нибудь, или идоложертвенное значит что–нибудь?</Verse>
        <Verse osisId="1Cor.10.20" sblId="1Cor 10:20" name="1 К Коринфянам 10:20" shortName="1 Кор 10:20" orderIndex="19">[Нет], но что язычники, принося жертвы, приносят бесам, а не Богу. Но я не хочу, чтобы вы были в общении с бесами.</Verse>
        <Verse osisId="1Cor.10.21" sblId="1Cor 10:21" name="1 К Коринфянам 10:21" shortName="1 Кор 10:21" orderIndex="20">Не можете пить чашу Господню и чашу бесовскую; не можете быть участниками в трапезе Господней и в трапезе бесовской.</Verse>
        <Verse osisId="1Cor.10.22" sblId="1Cor 10:22" name="1 К Коринфянам 10:22" shortName="1 Кор 10:22" orderIndex="21">Неужели мы [решимся] раздражать Господа? Разве мы сильнее Его?</Verse>
        <Verse osisId="1Cor.10.23" sblId="1Cor 10:23" name="1 К Коринфянам 10:23" shortName="1 Кор 10:23" orderIndex="22">Все мне позволительно, но не все полезно; все мне позволительно, но не все назидает.</Verse>
        <Verse osisId="1Cor.10.24" sblId="1Cor 10:24" name="1 К Коринфянам 10:24" shortName="1 Кор 10:24" orderIndex="23">Никто не ищи своего, но каждый [пользы] другого.</Verse>
        <Verse osisId="1Cor.10.25" sblId="1Cor 10:25" name="1 К Коринфянам 10:25" shortName="1 Кор 10:25" orderIndex="24">Все, что продается на торгу, ешьте без всякого исследования, для [спокойствия] совести;</Verse>
        <Verse osisId="1Cor.10.26" sblId="1Cor 10:26" name="1 К Коринфянам 10:26" shortName="1 Кор 10:26" orderIndex="25">ибо Господня земля, и что наполняет ее.</Verse>
        <Verse osisId="1Cor.10.27" sblId="1Cor 10:27" name="1 К Коринфянам 10:27" shortName="1 Кор 10:27" orderIndex="26">Если кто из неверных позовет вас, и вы захотите пойти, то все, предлагаемое вам, ешьте без всякого исследования, для [спокойствия] совести.</Verse>
        <Verse osisId="1Cor.10.28" sblId="1Cor 10:28" name="1 К Коринфянам 10:28" shortName="1 Кор 10:28" orderIndex="27">Но если кто скажет вам: это идоложертвенное, – то не ешьте ради того, кто объявил вам, и ради совести. Ибо Господня земля, и что наполняет ее.</Verse>
        <Verse osisId="1Cor.10.29" sblId="1Cor 10:29" name="1 К Коринфянам 10:29" shortName="1 Кор 10:29" orderIndex="28">Совесть же разумею не свою, а другого: ибо для чего моей свободе быть судимой чужою совестью?</Verse>
        <Verse osisId="1Cor.10.30" sblId="1Cor 10:30" name="1 К Коринфянам 10:30" shortName="1 Кор 10:30" orderIndex="29">Если я с благодарением принимаю [пищу], то для чего порицать меня за то, за что я благодарю?</Verse>
        <Verse osisId="1Cor.10.31" sblId="1Cor 10:31" name="1 К Коринфянам 10:31" shortName="1 Кор 10:31" orderIndex="30">Итак, едите ли, пьете ли, или иное что делаете, все делайте в славу Божию.</Verse>
        <Verse osisId="1Cor.10.32" sblId="1Cor 10:32" name="1 К Коринфянам 10:32" shortName="1 Кор 10:32" orderIndex="31">Не подавайте соблазна ни Иудеям, ни Еллинам, ни церкви Божией,</Verse>
        <Verse osisId="1Cor.10.33" sblId="1Cor 10:33" name="1 К Коринфянам 10:33" shortName="1 Кор 10:33" orderIndex="32">так, как и я угождаю всем во всем, ища не своей пользы, но [пользы] многих, чтобы они спаслись.</Verse>
      </verses>
    </Chapter>
    <Chapter osisId="1Cor.11" sblId="1Cor 11" name="1 К Коринфянам 11" shortName="1 Кор 11" orderIndex="10" versesCount="34">
      <verses>
        <Verse osisId="1Cor.11.1" sblId="1Cor 11:1" name="1 К Коринфянам 11:1" shortName="1 Кор 11:1" orderIndex="0">Будьте подражателями мне, как я Христу.</Verse>
        <Verse osisId="1Cor.11.2" sblId="1Cor 11:2" name="1 К Коринфянам 11:2" shortName="1 Кор 11:2" orderIndex="1">Хвалю вас, братия, что вы все мое помните и держите предания так, как я передал вам.</Verse>
        <Verse osisId="1Cor.11.3" sblId="1Cor 11:3" name="1 К Коринфянам 11:3" shortName="1 Кор 11:3" orderIndex="2">Хочу также, чтобы вы знали, что всякому мужу глава Христос, жене глава – муж, а Христу глава – Бог.</Verse>
        <Verse osisId="1Cor.11.4" sblId="1Cor 11:4" name="1 К Коринфянам 11:4" shortName="1 Кор 11:4" orderIndex="3">Всякий муж, молящийся или пророчествующий с покрытою головою, постыжает свою голову.</Verse>
        <Verse osisId="1Cor.11.5" sblId="1Cor 11:5" name="1 К Коринфянам 11:5" shortName="1 Кор 11:5" orderIndex="4">И всякая жена, молящаяся или пророчествующая с открытою головою, постыжает свою голову, ибо [это] то же, как если бы она была обритая.</Verse>
        <Verse osisId="1Cor.11.6" sblId="1Cor 11:6" name="1 К Коринфянам 11:6" shortName="1 Кор 11:6" orderIndex="5">Ибо если жена не хочет покрываться, то пусть и стрижется; а если жене стыдно быть остриженной или обритой, пусть покрывается.</Verse>
        <Verse osisId="1Cor.11.7" sblId="1Cor 11:7" name="1 К Коринфянам 11:7" shortName="1 Кор 11:7" orderIndex="6">Итак муж не должен покрывать голову, потому что он есть образ и слава Божия; а жена есть слава мужа.</Verse>
        <Verse osisId="1Cor.11.8" sblId="1Cor 11:8" name="1 К Коринфянам 11:8" shortName="1 Кор 11:8" orderIndex="7">Ибо не муж от жены, но жена от мужа;</Verse>
        <Verse osisId="1Cor.11.9" sblId="1Cor 11:9" name="1 К Коринфянам 11:9" shortName="1 Кор 11:9" orderIndex="8">и не муж создан для жены, но жена для мужа.</Verse>
        <Verse osisId="1Cor.11.10" sblId="1Cor 11:10" name="1 К Коринфянам 11:10" shortName="1 Кор 11:10" orderIndex="9">Посему жена и должна иметь на голове своей [знак] власти [над] [нею], для Ангелов.</Verse>
        <Verse osisId="1Cor.11.11" sblId="1Cor 11:11" name="1 К Коринфянам 11:11" shortName="1 Кор 11:11" orderIndex="10">Впрочем ни муж без жены, ни жена без мужа, в Господе.</Verse>
        <Verse osisId="1Cor.11.12" sblId="1Cor 11:12" name="1 К Коринфянам 11:12" shortName="1 Кор 11:12" orderIndex="11">Ибо как жена от мужа, так и муж через жену; все же – от Бога.</Verse>
        <Verse osisId="1Cor.11.13" sblId="1Cor 11:13" name="1 К Коринфянам 11:13" shortName="1 Кор 11:13" orderIndex="12">Рассудите сами, прилично ли жене молиться Богу с непокрытою [головою]?</Verse>
        <Verse osisId="1Cor.11.14" sblId="1Cor 11:14" name="1 К Коринфянам 11:14" shortName="1 Кор 11:14" orderIndex="13">Не сама ли природа учит вас, что если муж растит волосы, то это бесчестье для него,</Verse>
        <Verse osisId="1Cor.11.15" sblId="1Cor 11:15" name="1 К Коринфянам 11:15" shortName="1 Кор 11:15" orderIndex="14">но если жена растит волосы, для нее это честь, так как волосы даны ей вместо покрывала?</Verse>
        <Verse osisId="1Cor.11.16" sblId="1Cor 11:16" name="1 К Коринфянам 11:16" shortName="1 Кор 11:16" orderIndex="15">А если бы кто захотел спорить, то мы не имеем такого обычая, ни церкви Божии.</Verse>
        <Verse osisId="1Cor.11.17" sblId="1Cor 11:17" name="1 К Коринфянам 11:17" shortName="1 Кор 11:17" orderIndex="16">Но, предлагая сие, не хвалю [вас], что вы собираетесь не на лучшее, а на худшее.</Verse>
        <Verse osisId="1Cor.11.18" sblId="1Cor 11:18" name="1 К Коринфянам 11:18" shortName="1 Кор 11:18" orderIndex="17">Ибо, во–первых, слышу, что, когда вы собираетесь в церковь, между вами бывают разделения, чему отчасти и верю.</Verse>
        <Verse osisId="1Cor.11.19" sblId="1Cor 11:19" name="1 К Коринфянам 11:19" shortName="1 Кор 11:19" orderIndex="18">Ибо надлежит быть и разномыслиям между вами, дабы открылись между вами искусные.</Verse>
        <Verse osisId="1Cor.11.20" sblId="1Cor 11:20" name="1 К Коринфянам 11:20" shortName="1 Кор 11:20" orderIndex="19">Далее, вы собираетесь, [так, что это] не значит вкушать вечерю Господню;</Verse>
        <Verse osisId="1Cor.11.21" sblId="1Cor 11:21" name="1 К Коринфянам 11:21" shortName="1 Кор 11:21" orderIndex="20">ибо всякий поспешает прежде [других] есть свою пищу, [так] [что] иной бывает голоден, а иной упивается.</Verse>
        <Verse osisId="1Cor.11.22" sblId="1Cor 11:22" name="1 К Коринфянам 11:22" shortName="1 Кор 11:22" orderIndex="21">Разве у вас нет домов на то, чтобы есть и пить? Или пренебрегаете церковь Божию и унижаете неимущих? Что сказать вам? похвалить ли вас за это? Не похвалю.</Verse>
        <Verse osisId="1Cor.11.23" sblId="1Cor 11:23" name="1 К Коринфянам 11:23" shortName="1 Кор 11:23" orderIndex="22">Ибо я от [Самого] Господа принял то, что и вам передал, что Господь Иисус в ту ночь, в которую предан был, взял хлеб</Verse>
        <Verse osisId="1Cor.11.24" sblId="1Cor 11:24" name="1 К Коринфянам 11:24" shortName="1 Кор 11:24" orderIndex="23">и, возблагодарив, преломил и сказал: приимите, ядите, сие есть Тело Мое, за вас ломимое; сие творите в Мое воспоминание.</Verse>
        <Verse osisId="1Cor.11.25" sblId="1Cor 11:25" name="1 К Коринфянам 11:25" shortName="1 Кор 11:25" orderIndex="24">Также и чашу после вечери, и сказал: сия чаша есть новый завет в Моей Крови; сие творите, когда только будете пить, в Мое воспоминание.</Verse>
        <Verse osisId="1Cor.11.26" sblId="1Cor 11:26" name="1 К Коринфянам 11:26" shortName="1 Кор 11:26" orderIndex="25">Ибо всякий раз, когда вы едите хлеб сей и пьете чашу сию, смерть Господню возвещаете, доколе Он придет.</Verse>
        <Verse osisId="1Cor.11.27" sblId="1Cor 11:27" name="1 К Коринфянам 11:27" shortName="1 Кор 11:27" orderIndex="26">Посему, кто будет есть хлеб сей или пить чашу Господню недостойно, виновен будет против Тела и Крови Господней.</Verse>
        <Verse osisId="1Cor.11.28" sblId="1Cor 11:28" name="1 К Коринфянам 11:28" shortName="1 Кор 11:28" orderIndex="27">Да испытывает же себя человек, и таким образом пусть ест от хлеба сего и пьет из чаши сей.</Verse>
        <Verse osisId="1Cor.11.29" sblId="1Cor 11:29" name="1 К Коринфянам 11:29" shortName="1 Кор 11:29" orderIndex="28">Ибо, кто ест и пьет недостойно, тот ест и пьет осуждение себе, не рассуждая о Теле Господнем.</Verse>
        <Verse osisId="1Cor.11.30" sblId="1Cor 11:30" name="1 К Коринфянам 11:30" shortName="1 Кор 11:30" orderIndex="29">От того многие из вас немощны и больны и немало умирает.</Verse>
        <Verse osisId="1Cor.11.31" sblId="1Cor 11:31" name="1 К Коринфянам 11:31" shortName="1 Кор 11:31" orderIndex="30">Ибо если бы мы судили сами себя, то не были бы судимы.</Verse>
        <Verse osisId="1Cor.11.32" sblId="1Cor 11:32" name="1 К Коринфянам 11:32" shortName="1 Кор 11:32" orderIndex="31">Будучи же судимы, наказываемся от Господа, чтобы не быть осужденными с миром.</Verse>
        <Verse osisId="1Cor.11.33" sblId="1Cor 11:33" name="1 К Коринфянам 11:33" shortName="1 Кор 11:33" orderIndex="32">Посему, братия мои, собираясь на вечерю, друг друга ждите.</Verse>
        <Verse osisId="1Cor.11.34" sblId="1Cor 11:34" name="1 К Коринфянам 11:34" shortName="1 Кор 11:34" orderIndex="33">А если кто голоден, пусть ест дома, чтобы собираться вам не на осуждение. Прочее устрою, когда приду.</Verse>
      </verses>
    </Chapter>
    <Chapter osisId="1Cor.12" sblId="1Cor 12" name="1 К Коринфянам 12" shortName="1 Кор 12" orderIndex="11" versesCount="31">
      <verses>
        <Verse osisId="1Cor.12.1" sblId="1Cor 12:1" name="1 К Коринфянам 12:1" shortName="1 Кор 12:1" orderIndex="0">Не хочу оставить вас, братия, в неведении и о [дарах] духовных.</Verse>
        <Verse osisId="1Cor.12.2" sblId="1Cor 12:2" name="1 К Коринфянам 12:2" shortName="1 Кор 12:2" orderIndex="1">Знаете, что когда вы были язычниками, то ходили к безгласным идолам, так, как бы вели вас.</Verse>
        <Verse osisId="1Cor.12.3" sblId="1Cor 12:3" name="1 К Коринфянам 12:3" shortName="1 Кор 12:3" orderIndex="2">Потому сказываю вам, что никто, говорящий Духом Божиим, не произнесет анафемы на Иисуса, и никто не может назвать Иисуса Господом, как только Духом Святым.</Verse>
        <Verse osisId="1Cor.12.4" sblId="1Cor 12:4" name="1 К Коринфянам 12:4" shortName="1 Кор 12:4" orderIndex="3">Дары различны, но Дух один и тот же;</Verse>
        <Verse osisId="1Cor.12.5" sblId="1Cor 12:5" name="1 К Коринфянам 12:5" shortName="1 Кор 12:5" orderIndex="4">и служения различны, а Господь один и тот же;</Verse>
        <Verse osisId="1Cor.12.6" sblId="1Cor 12:6" name="1 К Коринфянам 12:6" shortName="1 Кор 12:6" orderIndex="5">и действия различны, а Бог один и тот же, производящий все во всех.</Verse>
        <Verse osisId="1Cor.12.7" sblId="1Cor 12:7" name="1 К Коринфянам 12:7" shortName="1 Кор 12:7" orderIndex="6">Но каждому дается проявление Духа на пользу.</Verse>
        <Verse osisId="1Cor.12.8" sblId="1Cor 12:8" name="1 К Коринфянам 12:8" shortName="1 Кор 12:8" orderIndex="7">Одному дается Духом слово мудрости, другому слово знания, тем же Духом;</Verse>
        <Verse osisId="1Cor.12.9" sblId="1Cor 12:9" name="1 К Коринфянам 12:9" shortName="1 Кор 12:9" orderIndex="8">иному вера, тем же Духом; иному дары исцелений, тем же Духом;</Verse>
        <Verse osisId="1Cor.12.10" sblId="1Cor 12:10" name="1 К Коринфянам 12:10" shortName="1 Кор 12:10" orderIndex="9">иному чудотворения, иному пророчество, иному различение духов, иному разные языки, иному истолкование языков.</Verse>
        <Verse osisId="1Cor.12.11" sblId="1Cor 12:11" name="1 К Коринфянам 12:11" shortName="1 Кор 12:11" orderIndex="10">Все же сие производит один и тот же Дух, разделяя каждому особо, как Ему угодно.</Verse>
        <Verse osisId="1Cor.12.12" sblId="1Cor 12:12" name="1 К Коринфянам 12:12" shortName="1 Кор 12:12" orderIndex="11">Ибо, как тело одно, но имеет многие члены, и все члены одного тела, хотя их и много, составляют одно тело, – так и Христос.</Verse>
        <Verse osisId="1Cor.12.13" sblId="1Cor 12:13" name="1 К Коринфянам 12:13" shortName="1 Кор 12:13" orderIndex="12">Ибо все мы одним Духом крестились в одно тело, Иудеи или Еллины, рабы или свободные, и все напоены одним Духом.</Verse>
        <Verse osisId="1Cor.12.14" sblId="1Cor 12:14" name="1 К Коринфянам 12:14" shortName="1 Кор 12:14" orderIndex="13">Тело же не из одного члена, но из многих.</Verse>
        <Verse osisId="1Cor.12.15" sblId="1Cor 12:15" name="1 К Коринфянам 12:15" shortName="1 Кор 12:15" orderIndex="14">Если нога скажет: я не принадлежу к телу, потому что я не рука, то неужели она потому не принадлежит к телу?</Verse>
        <Verse osisId="1Cor.12.16" sblId="1Cor 12:16" name="1 К Коринфянам 12:16" shortName="1 Кор 12:16" orderIndex="15">И если ухо скажет: я не принадлежу к телу, потому что я не глаз, то неужели оно потому не принадлежит к телу?</Verse>
        <Verse osisId="1Cor.12.17" sblId="1Cor 12:17" name="1 К Коринфянам 12:17" shortName="1 Кор 12:17" orderIndex="16">Если все тело глаз, то где слух? Если все слух, то где обоняние?</Verse>
        <Verse osisId="1Cor.12.18" sblId="1Cor 12:18" name="1 К Коринфянам 12:18" shortName="1 Кор 12:18" orderIndex="17">Но Бог расположил члены, каждый в [составе] тела, как Ему было угодно.</Verse>
        <Verse osisId="1Cor.12.19" sblId="1Cor 12:19" name="1 К Коринфянам 12:19" shortName="1 Кор 12:19" orderIndex="18">А если бы все были один член, то где [было бы] тело?</Verse>
        <Verse osisId="1Cor.12.20" sblId="1Cor 12:20" name="1 К Коринфянам 12:20" shortName="1 Кор 12:20" orderIndex="19">Но теперь членов много, а тело одно.</Verse>
        <Verse osisId="1Cor.12.21" sblId="1Cor 12:21" name="1 К Коринфянам 12:21" shortName="1 Кор 12:21" orderIndex="20">Не может глаз сказать руке: ты мне не надобна; или также голова ногам: вы мне не нужны.</Verse>
        <Verse osisId="1Cor.12.22" sblId="1Cor 12:22" name="1 К Коринфянам 12:22" shortName="1 Кор 12:22" orderIndex="21">Напротив, члены тела, которые кажутся слабейшими, гораздо нужнее,</Verse>
        <Verse osisId="1Cor.12.23" sblId="1Cor 12:23" name="1 К Коринфянам 12:23" shortName="1 Кор 12:23" orderIndex="22">и которые нам кажутся менее благородными в теле, о тех более прилагаем попечения;</Verse>
        <Verse osisId="1Cor.12.24" sblId="1Cor 12:24" name="1 К Коринфянам 12:24" shortName="1 Кор 12:24" orderIndex="23">и неблагообразные наши более благовидно покрываются, а благообразные наши не имеют [в том] нужды. Но Бог соразмерил тело, внушив о менее совершенном большее попечение,</Verse>
        <Verse osisId="1Cor.12.25" sblId="1Cor 12:25" name="1 К Коринфянам 12:25" shortName="1 Кор 12:25" orderIndex="24">дабы не было разделения в теле, а все члены одинаково заботились друг о друге.</Verse>
        <Verse osisId="1Cor.12.26" sblId="1Cor 12:26" name="1 К Коринфянам 12:26" shortName="1 Кор 12:26" orderIndex="25">Посему, страдает ли один член, страдают с ним все члены; славится ли один член, с ним радуются все члены.</Verse>
        <Verse osisId="1Cor.12.27" sblId="1Cor 12:27" name="1 К Коринфянам 12:27" shortName="1 Кор 12:27" orderIndex="26">И вы – тело Христово, а порознь – члены.</Verse>
        <Verse osisId="1Cor.12.28" sblId="1Cor 12:28" name="1 К Коринфянам 12:28" shortName="1 Кор 12:28" orderIndex="27">И иных Бог поставил в Церкви, во–первых, Апостолами, во–вторых, пророками, в–третьих, учителями; далее, [иным дал] силы [чудодейственные], также дары исцелений, вспоможения, управления, разные языки.</Verse>
        <Verse osisId="1Cor.12.29" sblId="1Cor 12:29" name="1 К Коринфянам 12:29" shortName="1 Кор 12:29" orderIndex="28">Все ли Апостолы? Все ли пророки? Все ли учители? Все ли чудотворцы?</Verse>
        <Verse osisId="1Cor.12.30" sblId="1Cor 12:30" name="1 К Коринфянам 12:30" shortName="1 Кор 12:30" orderIndex="29">Все ли имеют дары исцелений? Все ли говорят языками? Все ли истолкователи?</Verse>
        <Verse osisId="1Cor.12.31" sblId="1Cor 12:31" name="1 К Коринфянам 12:31" shortName="1 Кор 12:31" orderIndex="30">Ревнуйте о дарах больших, и я покажу вам путь еще превосходнейший.</Verse>
      </verses>
    </Chapter>
    <Chapter osisId="1Cor.13" sblId="1Cor 13" name="1 К Коринфянам 13" shortName="1 Кор 13" orderIndex="12" versesCount="13">
      <verses>
        <Verse osisId="1Cor.13.1" sblId="1Cor 13:1" name="1 К Коринфянам 13:1" shortName="1 Кор 13:1" orderIndex="0">Если я говорю языками человеческими и ангельскими, а любви не имею, то я – медь звенящая или кимвал звучащий.</Verse>
        <Verse osisId="1Cor.13.2" sblId="1Cor 13:2" name="1 К Коринфянам 13:2" shortName="1 Кор 13:2" orderIndex="1">Если имею [дар] пророчества, и знаю все тайны, и имею всякое познание и всю веру, так что [могу] и горы переставлять, а не имею любви, – то я ничто.</Verse>
        <Verse osisId="1Cor.13.3" sblId="1Cor 13:3" name="1 К Коринфянам 13:3" shortName="1 Кор 13:3" orderIndex="2">И если я раздам все имение мое и отдам тело мое на сожжение, а любви не имею, нет мне в том никакой пользы.</Verse>
        <Verse osisId="1Cor.13.4" sblId="1Cor 13:4" name="1 К Коринфянам 13:4" shortName="1 Кор 13:4" orderIndex="3">Любовь долготерпит, милосердствует, любовь не завидует, любовь не превозносится, не гордится,</Verse>
        <Verse osisId="1Cor.13.5" sblId="1Cor 13:5" name="1 К Коринфянам 13:5" shortName="1 Кор 13:5" orderIndex="4">не бесчинствует, не ищет своего, не раздражается, не мыслит зла,</Verse>
        <Verse osisId="1Cor.13.6" sblId="1Cor 13:6" name="1 К Коринфянам 13:6" shortName="1 Кор 13:6" orderIndex="5">не радуется неправде, а сорадуется истине;</Verse>
        <Verse osisId="1Cor.13.7" sblId="1Cor 13:7" name="1 К Коринфянам 13:7" shortName="1 Кор 13:7" orderIndex="6">все покрывает, всему верит, всего надеется, все переносит.</Verse>
        <Verse osisId="1Cor.13.8" sblId="1Cor 13:8" name="1 К Коринфянам 13:8" shortName="1 Кор 13:8" orderIndex="7">Любовь никогда не перестает, хотя и пророчества прекратятся, и языки умолкнут, и знание упразднится.</Verse>
        <Verse osisId="1Cor.13.9" sblId="1Cor 13:9" name="1 К Коринфянам 13:9" shortName="1 Кор 13:9" orderIndex="8">Ибо мы отчасти знаем, и отчасти пророчествуем;</Verse>
        <Verse osisId="1Cor.13.10" sblId="1Cor 13:10" name="1 К Коринфянам 13:10" shortName="1 Кор 13:10" orderIndex="9">когда же настанет совершенное, тогда то, что отчасти, прекратится.</Verse>
        <Verse osisId="1Cor.13.11" sblId="1Cor 13:11" name="1 К Коринфянам 13:11" shortName="1 Кор 13:11" orderIndex="10">Когда я был младенцем, то по–младенчески говорил, по–младенчески мыслил, по–младенчески рассуждал; а как стал мужем, то оставил младенческое.</Verse>
        <Verse osisId="1Cor.13.12" sblId="1Cor 13:12" name="1 К Коринфянам 13:12" shortName="1 Кор 13:12" orderIndex="11">Теперь мы видим как бы сквозь [тусклое] стекло, гадательно, тогда же лицем к лицу; теперь знаю я отчасти, а тогда познаю, подобно как я познан.</Verse>
        <Verse osisId="1Cor.13.13" sblId="1Cor 13:13" name="1 К Коринфянам 13:13" shortName="1 Кор 13:13" orderIndex="12">А теперь пребывают сии три: вера, надежда, любовь; но любовь из них больше.</Verse>
      </verses>
    </Chapter>
    <Chapter osisId="1Cor.14" sblId="1Cor 14" name="1 К Коринфянам 14" shortName="1 Кор 14" orderIndex="13" versesCount="40">
      <verses>
        <Verse osisId="1Cor.14.1" sblId="1Cor 14:1" name="1 К Коринфянам 14:1" shortName="1 Кор 14:1" orderIndex="0">Достигайте любви; ревнуйте о [дарах] духовных, особенно же о том, чтобы пророчествовать.</Verse>
        <Verse osisId="1Cor.14.2" sblId="1Cor 14:2" name="1 К Коринфянам 14:2" shortName="1 Кор 14:2" orderIndex="1">Ибо кто говорит на [незнакомом] языке, тот говорит не людям, а Богу; потому что никто не понимает [его], он тайны говорит духом;</Verse>
        <Verse osisId="1Cor.14.3" sblId="1Cor 14:3" name="1 К Коринфянам 14:3" shortName="1 Кор 14:3" orderIndex="2">а кто пророчествует, тот говорит людям в назидание, увещание и утешение.</Verse>
        <Verse osisId="1Cor.14.4" sblId="1Cor 14:4" name="1 К Коринфянам 14:4" shortName="1 Кор 14:4" orderIndex="3">Кто говорит на [незнакомом] языке, тот назидает себя; а кто пророчествует, тот назидает церковь.</Verse>
        <Verse osisId="1Cor.14.5" sblId="1Cor 14:5" name="1 К Коринфянам 14:5" shortName="1 Кор 14:5" orderIndex="4">Желаю, чтобы вы все говорили языками; но лучше, чтобы вы пророчествовали; ибо пророчествующий превосходнее того, кто говорит языками, разве он притом будет и изъяснять, чтобы церковь получила назидание.</Verse>
        <Verse osisId="1Cor.14.6" sblId="1Cor 14:6" name="1 К Коринфянам 14:6" shortName="1 Кор 14:6" orderIndex="5">Теперь, если я приду к вам, братия, и стану говорить на [незнакомых] языках, то какую принесу вам пользу, когда не изъяснюсь вам или откровением, или познанием, или пророчеством, или учением?</Verse>
        <Verse osisId="1Cor.14.7" sblId="1Cor 14:7" name="1 К Коринфянам 14:7" shortName="1 Кор 14:7" orderIndex="6">И бездушные [вещи], издающие звук, свирель или гусли, если не производят раздельных тонов, как распознать то, что играют на свирели или на гуслях?</Verse>
        <Verse osisId="1Cor.14.8" sblId="1Cor 14:8" name="1 К Коринфянам 14:8" shortName="1 Кор 14:8" orderIndex="7">И если труба будет издавать неопределенный звук, кто станет готовиться к сражению?</Verse>
        <Verse osisId="1Cor.14.9" sblId="1Cor 14:9" name="1 К Коринфянам 14:9" shortName="1 Кор 14:9" orderIndex="8">Так если и вы языком произносите невразумительные слова, то как узнают, что вы говорите? Вы будете говорить на ветер.</Verse>
        <Verse osisId="1Cor.14.10" sblId="1Cor 14:10" name="1 К Коринфянам 14:10" shortName="1 Кор 14:10" orderIndex="9">Сколько, например, различных слов в мире, и ни одного из них нет без значения.</Verse>
        <Verse osisId="1Cor.14.11" sblId="1Cor 14:11" name="1 К Коринфянам 14:11" shortName="1 Кор 14:11" orderIndex="10">Но если я не разумею значения слов, то я для говорящего чужестранец, и говорящий для меня чужестранец.</Verse>
        <Verse osisId="1Cor.14.12" sblId="1Cor 14:12" name="1 К Коринфянам 14:12" shortName="1 Кор 14:12" orderIndex="11">Так и вы, ревнуя о [дарах] духовных, старайтесь обогатиться [ими] к назиданию церкви.</Verse>
        <Verse osisId="1Cor.14.13" sblId="1Cor 14:13" name="1 К Коринфянам 14:13" shortName="1 Кор 14:13" orderIndex="12">А потому, говорящий на [незнакомом] языке, молись о даре истолкования.</Verse>
        <Verse osisId="1Cor.14.14" sblId="1Cor 14:14" name="1 К Коринфянам 14:14" shortName="1 Кор 14:14" orderIndex="13">Ибо когда я молюсь на [незнакомом] языке, то хотя дух мой и молится, но ум мой остается без плода.</Verse>
        <Verse osisId="1Cor.14.15" sblId="1Cor 14:15" name="1 К Коринфянам 14:15" shortName="1 Кор 14:15" orderIndex="14">Что же делать? Стану молиться духом, стану молиться и умом; буду петь духом, буду петь и умом.</Verse>
        <Verse osisId="1Cor.14.16" sblId="1Cor 14:16" name="1 К Коринфянам 14:16" shortName="1 Кор 14:16" orderIndex="15">Ибо если ты будешь благословлять духом, то стоящий на месте простолюдина как скажет: "аминь" при твоем благодарении? Ибо он не понимает, что ты говоришь.</Verse>
        <Verse osisId="1Cor.14.17" sblId="1Cor 14:17" name="1 К Коринфянам 14:17" shortName="1 Кор 14:17" orderIndex="16">Ты хорошо благодаришь, но другой не назидается.</Verse>
        <Verse osisId="1Cor.14.18" sblId="1Cor 14:18" name="1 К Коринфянам 14:18" shortName="1 Кор 14:18" orderIndex="17">Благодарю Бога моего: я более всех вас говорю языками;</Verse>
        <Verse osisId="1Cor.14.19" sblId="1Cor 14:19" name="1 К Коринфянам 14:19" shortName="1 Кор 14:19" orderIndex="18">но в церкви хочу лучше пять слов сказать умом моим, чтобы и других наставить, нежели тьму слов на [незнакомом] языке.</Verse>
        <Verse osisId="1Cor.14.20" sblId="1Cor 14:20" name="1 К Коринфянам 14:20" shortName="1 Кор 14:20" orderIndex="19">Братия! не будьте дети умом: на злое будьте младенцы, а по уму будьте совершеннолетни.</Verse>
        <Verse osisId="1Cor.14.21" sblId="1Cor 14:21" name="1 К Коринфянам 14:21" shortName="1 Кор 14:21" orderIndex="20">В законе написано: иными языками и иными устами буду говорить народу сему; но и тогда не послушают Меня, говорит Господь.</Verse>
        <Verse osisId="1Cor.14.22" sblId="1Cor 14:22" name="1 К Коринфянам 14:22" shortName="1 Кор 14:22" orderIndex="21">Итак языки суть знамение не для верующих, а для неверующих; пророчество же не для неверующих, а для верующих.</Verse>
        <Verse osisId="1Cor.14.23" sblId="1Cor 14:23" name="1 К Коринфянам 14:23" shortName="1 Кор 14:23" orderIndex="22">Если вся церковь сойдется вместе, и все станут говорить [незнакомыми] языками, и войдут к вам незнающие или неверующие, то не скажут ли, что вы беснуетесь?</Verse>
        <Verse osisId="1Cor.14.24" sblId="1Cor 14:24" name="1 К Коринфянам 14:24" shortName="1 Кор 14:24" orderIndex="23">Но когда все пророчествуют, и войдет кто неверующий или незнающий, то он всеми обличается, всеми судится.</Verse>
        <Verse osisId="1Cor.14.25" sblId="1Cor 14:25" name="1 К Коринфянам 14:25" shortName="1 Кор 14:25" orderIndex="24">И таким образом тайны сердца его обнаруживаются, и он падет ниц, поклонится Богу и скажет: истинно с вами Бог.</Verse>
        <Verse osisId="1Cor.14.26" sblId="1Cor 14:26" name="1 К Коринфянам 14:26" shortName="1 Кор 14:26" orderIndex="25">Итак что же, братия? Когда вы сходитесь, и у каждого из вас есть псалом, есть поучение, есть язык, есть откровение, есть истолкование, – все сие да будет к назиданию.</Verse>
        <Verse osisId="1Cor.14.27" sblId="1Cor 14:27" name="1 К Коринфянам 14:27" shortName="1 Кор 14:27" orderIndex="26">Если кто говорит на [незнакомом] языке, [говорите] двое, или много трое, и то порознь, а один изъясняй.</Verse>
        <Verse osisId="1Cor.14.28" sblId="1Cor 14:28" name="1 К Коринфянам 14:28" shortName="1 Кор 14:28" orderIndex="27">Если же не будет истолкователя, то молчи в церкви, а говори себе и Богу.</Verse>
        <Verse osisId="1Cor.14.29" sblId="1Cor 14:29" name="1 К Коринфянам 14:29" shortName="1 Кор 14:29" orderIndex="28">И пророки пусть говорят двое или трое, а прочие пусть рассуждают.</Verse>
        <Verse osisId="1Cor.14.30" sblId="1Cor 14:30" name="1 К Коринфянам 14:30" shortName="1 Кор 14:30" orderIndex="29">Если же другому из сидящих будет откровение, то первый молчи.</Verse>
        <Verse osisId="1Cor.14.31" sblId="1Cor 14:31" name="1 К Коринфянам 14:31" shortName="1 Кор 14:31" orderIndex="30">Ибо все один за другим можете пророчествовать, чтобы всем поучаться и всем получать утешение.</Verse>
        <Verse osisId="1Cor.14.32" sblId="1Cor 14:32" name="1 К Коринфянам 14:32" shortName="1 Кор 14:32" orderIndex="31">И духи пророческие послушны пророкам,</Verse>
        <Verse osisId="1Cor.14.33" sblId="1Cor 14:33" name="1 К Коринфянам 14:33" shortName="1 Кор 14:33" orderIndex="32">потому что Бог не есть [Бог] неустройства, но мира. Так [бывает] во всех церквах у святых.</Verse>
        <Verse osisId="1Cor.14.34" sblId="1Cor 14:34" name="1 К Коринфянам 14:34" shortName="1 Кор 14:34" orderIndex="33">Жены ваши в церквах да молчат, ибо не позволено им говорить, а быть в подчинении, как и закон говорит.</Verse>
        <Verse osisId="1Cor.14.35" sblId="1Cor 14:35" name="1 К Коринфянам 14:35" shortName="1 Кор 14:35" orderIndex="34">Если же они хотят чему научиться, пусть спрашивают [о том] дома у мужей своих; ибо неприлично жене говорить в церкви.</Verse>
        <Verse osisId="1Cor.14.36" sblId="1Cor 14:36" name="1 К Коринфянам 14:36" shortName="1 Кор 14:36" orderIndex="35">Разве от вас вышло слово Божие? Или до вас одних достигло?</Verse>
        <Verse osisId="1Cor.14.37" sblId="1Cor 14:37" name="1 К Коринфянам 14:37" shortName="1 Кор 14:37" orderIndex="36">Если кто почитает себя пророком или духовным, тот да разумеет, что я пишу вам, ибо это заповеди Господни.</Verse>
        <Verse osisId="1Cor.14.38" sblId="1Cor 14:38" name="1 К Коринфянам 14:38" shortName="1 Кор 14:38" orderIndex="37">А кто не разумеет, пусть не разумеет.</Verse>
        <Verse osisId="1Cor.14.39" sblId="1Cor 14:39" name="1 К Коринфянам 14:39" shortName="1 Кор 14:39" orderIndex="38">Итак, братия, ревнуйте о том, чтобы пророчествовать, но не запрещайте говорить и языками;</Verse>
        <Verse osisId="1Cor.14.40" sblId="1Cor 14:40" name="1 К Коринфянам 14:40" shortName="1 Кор 14:40" orderIndex="39">только все должно быть благопристойно и чинно.</Verse>
      </verses>
    </Chapter>
    <Chapter osisId="1Cor.15" sblId="1Cor 15" name="1 К Коринфянам 15" shortName="1 Кор 15" orderIndex="14" versesCount="58">
      <verses>
        <Verse osisId="1Cor.15.1" sblId="1Cor 15:1" name="1 К Коринфянам 15:1" shortName="1 Кор 15:1" orderIndex="0">Напоминаю вам, братия, Евангелие, которое я благовествовал вам, которое вы и приняли, в котором и утвердились,</Verse>
        <Verse osisId="1Cor.15.2" sblId="1Cor 15:2" name="1 К Коринфянам 15:2" shortName="1 Кор 15:2" orderIndex="1">которым и спасаетесь, если преподанное удерживаете так, как я благовествовал вам, если только не тщетно уверовали.</Verse>
        <Verse osisId="1Cor.15.3" sblId="1Cor 15:3" name="1 К Коринфянам 15:3" shortName="1 Кор 15:3" orderIndex="2">Ибо я первоначально преподал вам, что и [сам] принял, [то] [есть], что Христос умер за грехи наши, по Писанию,</Verse>
        <Verse osisId="1Cor.15.4" sblId="1Cor 15:4" name="1 К Коринфянам 15:4" shortName="1 Кор 15:4" orderIndex="3">и что Он погребен был, и что воскрес в третий день, по Писанию,</Verse>
        <Verse osisId="1Cor.15.5" sblId="1Cor 15:5" name="1 К Коринфянам 15:5" shortName="1 Кор 15:5" orderIndex="4">и что явился Кифе, потом двенадцати;</Verse>
        <Verse osisId="1Cor.15.6" sblId="1Cor 15:6" name="1 К Коринфянам 15:6" shortName="1 Кор 15:6" orderIndex="5">потом явился более нежели пятистам братий в одно время, из которых большая часть доныне в живых, а некоторые и почили;</Verse>
        <Verse osisId="1Cor.15.7" sblId="1Cor 15:7" name="1 К Коринфянам 15:7" shortName="1 Кор 15:7" orderIndex="6">потом явился Иакову, также всем Апостолам;</Verse>
        <Verse osisId="1Cor.15.8" sblId="1Cor 15:8" name="1 К Коринфянам 15:8" shortName="1 Кор 15:8" orderIndex="7">а после всех явился и мне, как некоему извергу.</Verse>
        <Verse osisId="1Cor.15.9" sblId="1Cor 15:9" name="1 К Коринфянам 15:9" shortName="1 Кор 15:9" orderIndex="8">Ибо я наименьший из Апостолов, и недостоин называться Апостолом, потому что гнал церковь Божию.</Verse>
        <Verse osisId="1Cor.15.10" sblId="1Cor 15:10" name="1 К Коринфянам 15:10" shortName="1 Кор 15:10" orderIndex="9">Но благодатию Божиею есмь то, что есмь; и благодать Его во мне не была тщетна, но я более всех их потрудился: не я, впрочем, а благодать Божия, которая со мною.</Verse>
        <Verse osisId="1Cor.15.11" sblId="1Cor 15:11" name="1 К Коринфянам 15:11" shortName="1 Кор 15:11" orderIndex="10">Итак я ли, они ли, мы так проповедуем, и вы так уверовали.</Verse>
        <Verse osisId="1Cor.15.12" sblId="1Cor 15:12" name="1 К Коринфянам 15:12" shortName="1 Кор 15:12" orderIndex="11">Если же о Христе проповедуется, что Он воскрес из мертвых, то как некоторые из вас говорят, что нет воскресения мертвых?</Verse>
        <Verse osisId="1Cor.15.13" sblId="1Cor 15:13" name="1 К Коринфянам 15:13" shortName="1 Кор 15:13" orderIndex="12">Если нет воскресения мертвых, то и Христос не воскрес;</Verse>
        <Verse osisId="1Cor.15.14" sblId="1Cor 15:14" name="1 К Коринфянам 15:14" shortName="1 Кор 15:14" orderIndex="13">а если Христос не воскрес, то и проповедь наша тщетна, тщетна и вера ваша.</Verse>
        <Verse osisId="1Cor.15.15" sblId="1Cor 15:15" name="1 К Коринфянам 15:15" shortName="1 Кор 15:15" orderIndex="14">Притом мы оказались бы и лжесвидетелями о Боге, потому что свидетельствовали бы о Боге, что Он воскресил Христа, Которого Он не воскрешал, если, [то есть], мертвые не воскресают;</Verse>
        <Verse osisId="1Cor.15.16" sblId="1Cor 15:16" name="1 К Коринфянам 15:16" shortName="1 Кор 15:16" orderIndex="15">ибо если мертвые не воскресают, то и Христос не воскрес.</Verse>
        <Verse osisId="1Cor.15.17" sblId="1Cor 15:17" name="1 К Коринфянам 15:17" shortName="1 Кор 15:17" orderIndex="16">А если Христос не воскрес, то вера ваша тщетна: вы еще во грехах ваших.</Verse>
        <Verse osisId="1Cor.15.18" sblId="1Cor 15:18" name="1 К Коринфянам 15:18" shortName="1 Кор 15:18" orderIndex="17">Поэтому и умершие во Христе погибли.</Verse>
        <Verse osisId="1Cor.15.19" sblId="1Cor 15:19" name="1 К Коринфянам 15:19" shortName="1 Кор 15:19" orderIndex="18">И если мы в этой только жизни надеемся на Христа, то мы несчастнее всех человеков.</Verse>
        <Verse osisId="1Cor.15.20" sblId="1Cor 15:20" name="1 К Коринфянам 15:20" shortName="1 Кор 15:20" orderIndex="19">Но Христос воскрес из мертвых, первенец из умерших.</Verse>
        <Verse osisId="1Cor.15.21" sblId="1Cor 15:21" name="1 К Коринфянам 15:21" shortName="1 Кор 15:21" orderIndex="20">Ибо, как смерть через человека, [так] через человека и воскресение мертвых.</Verse>
        <Verse osisId="1Cor.15.22" sblId="1Cor 15:22" name="1 К Коринфянам 15:22" shortName="1 Кор 15:22" orderIndex="21">Как в Адаме все умирают, так во Христе все оживут,</Verse>
        <Verse osisId="1Cor.15.23" sblId="1Cor 15:23" name="1 К Коринфянам 15:23" shortName="1 Кор 15:23" orderIndex="22">каждый в своем порядке: первенец Христос, потом Христовы, в пришествие Его.</Verse>
        <Verse osisId="1Cor.15.24" sblId="1Cor 15:24" name="1 К Коринфянам 15:24" shortName="1 Кор 15:24" orderIndex="23">А затем конец, когда Он предаст Царство Богу и Отцу, когда упразднит всякое начальство и всякую власть и силу.</Verse>
        <Verse osisId="1Cor.15.25" sblId="1Cor 15:25" name="1 К Коринфянам 15:25" shortName="1 Кор 15:25" orderIndex="24">Ибо Ему надлежит царствовать, доколе низложит всех врагов под ноги Свои.</Verse>
        <Verse osisId="1Cor.15.26" sblId="1Cor 15:26" name="1 К Коринфянам 15:26" shortName="1 Кор 15:26" orderIndex="25">Последний же враг истребится – смерть,</Verse>
        <Verse osisId="1Cor.15.27" sblId="1Cor 15:27" name="1 К Коринфянам 15:27" shortName="1 Кор 15:27" orderIndex="26">потому что все покорил под ноги Его. Когда же сказано, что [Ему] все покорено, то ясно, что кроме Того, Который покорил Ему все.</Verse>
        <Verse osisId="1Cor.15.28" sblId="1Cor 15:28" name="1 К Коринфянам 15:28" shortName="1 Кор 15:28" orderIndex="27">Когда же все покорит Ему, тогда и Сам Сын покорится Покорившему все Ему, да будет Бог все во всем.</Verse>
        <Verse osisId="1Cor.15.29" sblId="1Cor 15:29" name="1 К Коринфянам 15:29" shortName="1 Кор 15:29" orderIndex="28">Иначе, что делают крестящиеся для мертвых? Если мертвые совсем не воскресают, то для чего и крестятся для мертвых?</Verse>
        <Verse osisId="1Cor.15.30" sblId="1Cor 15:30" name="1 К Коринфянам 15:30" shortName="1 Кор 15:30" orderIndex="29">Для чего и мы ежечасно подвергаемся бедствиям?</Verse>
        <Verse osisId="1Cor.15.31" sblId="1Cor 15:31" name="1 К Коринфянам 15:31" shortName="1 Кор 15:31" orderIndex="30">Я каждый день умираю: свидетельствуюсь в том похвалою вашею, братия, которую я имею во Христе Иисусе, Господе нашем.</Verse>
        <Verse osisId="1Cor.15.32" sblId="1Cor 15:32" name="1 К Коринфянам 15:32" shortName="1 Кор 15:32" orderIndex="31">По [рассуждению] человеческому, когда я боролся со зверями в Ефесе, какая мне польза, если мертвые не воскресают? Станем есть и пить, ибо завтра умрем!</Verse>
        <Verse osisId="1Cor.15.33" sblId="1Cor 15:33" name="1 К Коринфянам 15:33" shortName="1 Кор 15:33" orderIndex="32">Не обманывайтесь: худые сообщества развращают добрые нравы.</Verse>
        <Verse osisId="1Cor.15.34" sblId="1Cor 15:34" name="1 К Коринфянам 15:34" shortName="1 Кор 15:34" orderIndex="33">Отрезвитесь, как должно, и не грешите; ибо, к стыду вашему скажу, некоторые из вас не знают Бога.</Verse>
        <Verse osisId="1Cor.15.35" sblId="1Cor 15:35" name="1 К Коринфянам 15:35" shortName="1 Кор 15:35" orderIndex="34">Но скажет кто–нибудь: как воскреснут мертвые? и в каком теле придут?</Verse>
        <Verse osisId="1Cor.15.36" sblId="1Cor 15:36" name="1 К Коринфянам 15:36" shortName="1 Кор 15:36" orderIndex="35">Безрассудный! то, что ты сеешь, не оживет, если не умрет.</Verse>
        <Verse osisId="1Cor.15.37" sblId="1Cor 15:37" name="1 К Коринфянам 15:37" shortName="1 Кор 15:37" orderIndex="36">И когда ты сеешь, то сеешь не тело будущее, а голое зерно, какое случится, пшеничное или другое какое;</Verse>
        <Verse osisId="1Cor.15.38" sblId="1Cor 15:38" name="1 К Коринфянам 15:38" shortName="1 Кор 15:38" orderIndex="37">но Бог дает ему тело, как хочет, и каждому семени свое тело.</Verse>
        <Verse osisId="1Cor.15.39" sblId="1Cor 15:39" name="1 К Коринфянам 15:39" shortName="1 Кор 15:39" orderIndex="38">Не всякая плоть такая же плоть; но иная плоть у человеков, иная плоть у скотов, иная у рыб, иная у птиц.</Verse>
        <Verse osisId="1Cor.15.40" sblId="1Cor 15:40" name="1 К Коринфянам 15:40" shortName="1 Кор 15:40" orderIndex="39">Есть тела небесные и тела земные; но иная слава небесных, иная земных.</Verse>
        <Verse osisId="1Cor.15.41" sblId="1Cor 15:41" name="1 К Коринфянам 15:41" shortName="1 Кор 15:41" orderIndex="40">Иная слава солнца, иная слава луны, иная звезд; и звезда от звезды разнится в славе.</Verse>
        <Verse osisId="1Cor.15.42" sblId="1Cor 15:42" name="1 К Коринфянам 15:42" shortName="1 Кор 15:42" orderIndex="41">Так и при воскресении мертвых: сеется в тлении, восстает в нетлении;</Verse>
        <Verse osisId="1Cor.15.43" sblId="1Cor 15:43" name="1 К Коринфянам 15:43" shortName="1 Кор 15:43" orderIndex="42">сеется в уничижении, восстает в славе; сеется в немощи, восстает в силе;</Verse>
        <Verse osisId="1Cor.15.44" sblId="1Cor 15:44" name="1 К Коринфянам 15:44" shortName="1 Кор 15:44" orderIndex="43">сеется тело душевное, восстает тело духовное. Есть тело душевное, есть тело и духовное.</Verse>
        <Verse osisId="1Cor.15.45" sblId="1Cor 15:45" name="1 К Коринфянам 15:45" shortName="1 Кор 15:45" orderIndex="44">Так и написано: первый человек Адам стал душею живущею; а последний Адам есть дух животворящий.</Verse>
        <Verse osisId="1Cor.15.46" sblId="1Cor 15:46" name="1 К Коринфянам 15:46" shortName="1 Кор 15:46" orderIndex="45">Но не духовное прежде, а душевное, потом духовное.</Verse>
        <Verse osisId="1Cor.15.47" sblId="1Cor 15:47" name="1 К Коринфянам 15:47" shortName="1 Кор 15:47" orderIndex="46">Первый человек – из земли, перстный; второй человек – Господь с неба.</Verse>
        <Verse osisId="1Cor.15.48" sblId="1Cor 15:48" name="1 К Коринфянам 15:48" shortName="1 Кор 15:48" orderIndex="47">Каков перстный, таковы и перстные; и каков небесный, таковы и небесные.</Verse>
        <Verse osisId="1Cor.15.49" sblId="1Cor 15:49" name="1 К Коринфянам 15:49" shortName="1 Кор 15:49" orderIndex="48">И как мы носили образ перстного, будем носить и образ небесного.</Verse>
        <Verse osisId="1Cor.15.50" sblId="1Cor 15:50" name="1 К Коринфянам 15:50" shortName="1 Кор 15:50" orderIndex="49">Но то скажу [вам], братия, что плоть и кровь не могут наследовать Царствия Божия, и тление не наследует нетления.</Verse>
        <Verse osisId="1Cor.15.51" sblId="1Cor 15:51" name="1 К Коринфянам 15:51" shortName="1 Кор 15:51" orderIndex="50">Говорю вам тайну: не все мы умрем, но все изменимся</Verse>
        <Verse osisId="1Cor.15.52" sblId="1Cor 15:52" name="1 К Коринфянам 15:52" shortName="1 Кор 15:52" orderIndex="51">вдруг, во мгновение ока, при последней трубе; ибо вострубит, и мертвые воскреснут нетленными, а мы изменимся.</Verse>
        <Verse osisId="1Cor.15.53" sblId="1Cor 15:53" name="1 К Коринфянам 15:53" shortName="1 Кор 15:53" orderIndex="52">Ибо тленному сему надлежит облечься в нетление, и смертному сему облечься в бессмертие.</Verse>
        <Verse osisId="1Cor.15.54" sblId="1Cor 15:54" name="1 К Коринфянам 15:54" shortName="1 Кор 15:54" orderIndex="53">Когда же тленное сие облечется в нетление и смертное сие облечется в бессмертие, тогда сбудется слово написанное: поглощена смерть победою.</Verse>
        <Verse osisId="1Cor.15.55" sblId="1Cor 15:55" name="1 К Коринфянам 15:55" shortName="1 Кор 15:55" orderIndex="54">Смерть! где твое жало? ад! где твоя победа?</Verse>
        <Verse osisId="1Cor.15.56" sblId="1Cor 15:56" name="1 К Коринфянам 15:56" shortName="1 Кор 15:56" orderIndex="55">Жало же смерти – грех; а сила греха – закон.</Verse>
        <Verse osisId="1Cor.15.57" sblId="1Cor 15:57" name="1 К Коринфянам 15:57" shortName="1 Кор 15:57" orderIndex="56">Благодарение Богу, даровавшему нам победу Господом нашим Иисусом Христом!</Verse>
        <Verse osisId="1Cor.15.58" sblId="1Cor 15:58" name="1 К Коринфянам 15:58" shortName="1 Кор 15:58" orderIndex="57">Итак, братия мои возлюбленные, будьте тверды, непоколебимы, всегда преуспевайте в деле Господнем, зная, что труд ваш не тщетен пред Господом.</Verse>
      </verses>
    </Chapter>
    <Chapter osisId="1Cor.16" sblId="1Cor 16" name="1 К Коринфянам 16" shortName="1 Кор 16" orderIndex="15" versesCount="24">
      <verses>
        <Verse osisId="1Cor.16.1" sblId="1Cor 16:1" name="1 К Коринфянам 16:1" shortName="1 Кор 16:1" orderIndex="0">При сборе же для святых поступайте так, как я установил в церквах Галатийских.</Verse>
        <Verse osisId="1Cor.16.2" sblId="1Cor 16:2" name="1 К Коринфянам 16:2" shortName="1 Кор 16:2" orderIndex="1">В первый день недели каждый из вас пусть отлагает у себя и сберегает, сколько позволит ему состояние, чтобы не делать сборов, когда я приду.</Verse>
        <Verse osisId="1Cor.16.3" sblId="1Cor 16:3" name="1 К Коринфянам 16:3" shortName="1 Кор 16:3" orderIndex="2">Когда же приду, то, которых вы изберете, тех отправлю с письмами, для доставления вашего подаяния в Иерусалим.</Verse>
        <Verse osisId="1Cor.16.4" sblId="1Cor 16:4" name="1 К Коринфянам 16:4" shortName="1 Кор 16:4" orderIndex="3">А если прилично будет и мне отправиться, то они со мной пойдут.</Verse>
        <Verse osisId="1Cor.16.5" sblId="1Cor 16:5" name="1 К Коринфянам 16:5" shortName="1 Кор 16:5" orderIndex="4">Я приду к вам, когда пройду Македонию; ибо я иду через Македонию.</Verse>
        <Verse osisId="1Cor.16.6" sblId="1Cor 16:6" name="1 К Коринфянам 16:6" shortName="1 Кор 16:6" orderIndex="5">У вас же, может быть, поживу, или и перезимую, чтобы вы меня проводили, куда пойду.</Verse>
        <Verse osisId="1Cor.16.7" sblId="1Cor 16:7" name="1 К Коринфянам 16:7" shortName="1 Кор 16:7" orderIndex="6">Ибо я не хочу видеться с вами теперь мимоходом, а надеюсь пробыть у вас несколько времени, если Господь позволит.</Verse>
        <Verse osisId="1Cor.16.8" sblId="1Cor 16:8" name="1 К Коринфянам 16:8" shortName="1 Кор 16:8" orderIndex="7">В Ефесе же я пробуду до Пятидесятницы,</Verse>
        <Verse osisId="1Cor.16.9" sblId="1Cor 16:9" name="1 К Коринфянам 16:9" shortName="1 Кор 16:9" orderIndex="8">ибо для меня отверста великая и широкая дверь, и противников много.</Verse>
        <Verse osisId="1Cor.16.10" sblId="1Cor 16:10" name="1 К Коринфянам 16:10" shortName="1 Кор 16:10" orderIndex="9">Если же придет к вам Тимофей, смотрите, чтобы он был у вас безопасен; ибо он делает дело Господне, как и я.</Verse>
        <Verse osisId="1Cor.16.11" sblId="1Cor 16:11" name="1 К Коринфянам 16:11" shortName="1 Кор 16:11" orderIndex="10">Посему никто не пренебрегай его, но проводите его с миром, чтобы он пришел ко мне, ибо я жду его с братиями.</Verse>
        <Verse osisId="1Cor.16.12" sblId="1Cor 16:12" name="1 К Коринфянам 16:12" shortName="1 Кор 16:12" orderIndex="11">А что до брата Аполлоса, я очень просил его, чтобы он с братиями пошел к вам; но он никак не хотел идти ныне, а придет, когда ему будет удобно.</Verse>
        <Verse osisId="1Cor.16.13" sblId="1Cor 16:13" name="1 К Коринфянам 16:13" shortName="1 Кор 16:13" orderIndex="12">Бодрствуйте, стойте в вере, будьте мужественны, тверды.</Verse>
        <Verse osisId="1Cor.16.14" sblId="1Cor 16:14" name="1 К Коринфянам 16:14" shortName="1 Кор 16:14" orderIndex="13">Все у вас да будет с любовью.</Verse>
        <Verse osisId="1Cor.16.15" sblId="1Cor 16:15" name="1 К Коринфянам 16:15" shortName="1 Кор 16:15" orderIndex="14">Прошу вас, братия (вы знаете семейство Стефаново, что оно есть начаток Ахаии и что они посвятили себя на служение святым),</Verse>
        <Verse osisId="1Cor.16.16" sblId="1Cor 16:16" name="1 К Коринфянам 16:16" shortName="1 Кор 16:16" orderIndex="15">будьте и вы почтительны к таковым и ко всякому содействующему и трудящемуся.</Verse>
        <Verse osisId="1Cor.16.17" sblId="1Cor 16:17" name="1 К Коринфянам 16:17" shortName="1 Кор 16:17" orderIndex="16">Я рад прибытию Стефана, Фортуната и Ахаика: они восполнили для меня отсутствие ваше,</Verse>
        <Verse osisId="1Cor.16.18" sblId="1Cor 16:18" name="1 К Коринфянам 16:18" shortName="1 Кор 16:18" orderIndex="17">ибо они мой и ваш дух успокоили. Почитайте таковых.</Verse>
        <Verse osisId="1Cor.16.19" sblId="1Cor 16:19" name="1 К Коринфянам 16:19" shortName="1 Кор 16:19" orderIndex="18">Приветствуют вас церкви Асийские; приветствуют вас усердно в Господе Акила и Прискилла с домашнею их церковью.</Verse>
        <Verse osisId="1Cor.16.20" sblId="1Cor 16:20" name="1 К Коринфянам 16:20" shortName="1 Кор 16:20" orderIndex="19">Приветствуют вас все братия. Приветствуйте друг друга святым целованием.</Verse>
        <Verse osisId="1Cor.16.21" sblId="1Cor 16:21" name="1 К Коринфянам 16:21" shortName="1 Кор 16:21" orderIndex="20">Мое, Павлово, приветствие собственноручно.</Verse>
        <Verse osisId="1Cor.16.22" sblId="1Cor 16:22" name="1 К Коринфянам 16:22" shortName="1 Кор 16:22" orderIndex="21">Кто не любит Господа Иисуса Христа, анафема, маранафа.</Verse>
        <Verse osisId="1Cor.16.23" sblId="1Cor 16:23" name="1 К Коринфянам 16:23" shortName="1 Кор 16:23" orderIndex="22">Благодать Господа нашего Иисуса Христа с вами,</Verse>
        <Verse osisId="1Cor.16.24" sblId="1Cor 16:24" name="1 К Коринфянам 16:24" shortName="1 Кор 16:24" orderIndex="23">и любовь моя со всеми вами во Христе Иисусе. Аминь.</Verse>
      </verses>
    </Chapter>
  </chapters>
</Book>